Workbook
Name scenario: 'Drivers'!$D$6
Name share_price: 'Drivers'!$D$7
Name valuation_date: 'Drivers'!$D$8
Name bs_date: 'Drivers'!$D$9
Name fy1_end: 'Drivers'!$D$10
Name exit_date: 'Drivers'!$D$11
Name exit_date2: 'Drivers'!$D$12
Name shares_diluted: 'Drivers'!$D$13
Name cash_bs: 'Drivers'!$D$14
Name total_debt: 'Drivers'!$D$15
Name net_debt: 'Drivers'!$D$16
Name fee_2026: 'Drivers'!$D$17
Name market_cap: 'Drivers'!$D$18
Name enterprise_value: 'Drivers'!$D$19
Name risk_free_rate: 'Drivers'!$D$22
Name beta: 'Drivers'!$D$23
Name equity_risk_premium: 'Drivers'!$D$24
Name cost_of_equity: 'Drivers'!$D$25
Name kd_pretax: 'Drivers'!$D$26
Name kd_tax: 'Drivers'!$D$27
Name debt_weight: 'Drivers'!$D$28
Name wacc_rate: 'Drivers'!$D$29
Name min_cash_months: 'Drivers'!$D$32
Name creep: 'Drivers'!$D$33
Name rep_px_2026: 'Drivers'!$D$34
Name rep_px_growth: 'Drivers'!$D$35
Name hurdle_irr: 'Drivers'!$D$36
Name wacc_step: 'Drivers'!$D$37
Name g_step: 'Drivers'!$D$38
Name pe_step: 'Drivers'!$D$39
Name prob_bear: 'Drivers'!$F$43
Name prob_base: 'Drivers'!$G$43
Name prob_bull: 'Drivers'!$H$43
Name tg_bear: 'Drivers'!$F$44
Name tg_base: 'Drivers'!$G$44
Name tg_bull: 'Drivers'!$H$44
Name exit_pe_bear: 'Drivers'!$F$45
Name exit_pe_base: 'Drivers'!$G$45
Name exit_pe_bull: 'Drivers'!$H$45
Name fy25_rev_ucan: 'Drivers'!$D$48
Name fy25_rev_emea: 'Drivers'!$D$49
Name fy25_rev_latam: 'Drivers'!$D$50
Name fy25_rev_apac: 'Drivers'!$D$51
Name cash_to_amort: 'Drivers'!$I$56:$R$56
Name da_pct: 'Drivers'!$I$57:$R$57
Name sbc_pct: 'Drivers'!$I$58:$R$58
Name capex_pct: 'Drivers'!$I$59:$R$59
Name wc_pct: 'Drivers'!$I$60:$R$60
Name tax_rate: 'Drivers'!$I$61:$R$61
Name int_rate: 'Drivers'!$I$62:$R$62
Name cash_yield: 'Drivers'!$I$63:$R$63
Name oneoff: 'Drivers'!$I$64:$R$64
Name gross_debt: 'Drivers'!$I$65:$R$65
Name g_ucan_bear: 'Drivers'!$I$69:$R$69
Name g_ucan_base: 'Drivers'!$I$70:$R$70
Name g_ucan_bull: 'Drivers'!$I$71:$R$71
Name g_emea_bear: 'Drivers'!$I$72:$R$72
Name g_emea_base: 'Drivers'!$I$73:$R$73
Name g_emea_bull: 'Drivers'!$I$74:$R$74
Name g_latam_bear: 'Drivers'!$I$75:$R$75

Sheet Summary
B1: Netflix, Inc. (NASDAQ: NFLX)
B2: Built 2026-10-23 after the Q3 2026 print, for a 2-3 year hold. Calendar fiscal year; shares post the 10-for-1 split.
B3: Blue = input Black = formula Green = cross-sheet link $ in millions except per share; shares in millions (post-split)
B5: MARKET
B6: Share price | C6: $ | D6: ='Drivers'!$D$7 | E6: ='Drivers'!$D$8
B7: Diluted shares | C7: mm | D7: ='Drivers'!$D$13
B8: Market capitalization | C8: $mm | D8: ='Drivers'!$D$18
B9: Net debt (9/30/26) | C9: $mm | D9: ='Drivers'!$D$16
B10: Enterprise value | C10: $mm | D10: ='Drivers'!$D$19
B11: P/E, FY26E ex the fee / FY27E (base) | C11: x | D11: ='Drivers'!$D$7/'Scenarios'!G14 | E11: ='Drivers'!$D$7/'Scenarios'!G15
B12: EV / EBIT, FY26E (base) | C12: x | D12: ='Scenarios'!D244
B13: Free cash flow yield, FY26E ex the fee (base) | C13: % | D13: ='Scenarios'!I208/'Drivers'!$D$18
B14: Buyback yield, FY26E (base) | C14: % | D14: =-'Scenarios'!I213/'Drivers'!$D$18
B15: Street price target, average / 10-year median P/E (Earnings Desk) | C15: $ | D15: ='Drivers'!$D$107 | E15: 55
B17: VALUE BY SCENARIO
D18: Bear | E18: Base | F18: Bull | G18: Weighted
B19: Probability | C19: % | D19: ='Scenarios'!F7 | E19: ='Scenarios'!G7 | F19: ='Scenarios'!H7
B20: DCF value per share | C20: $ | D20: ='Scenarios'!F24 | E20: ='Scenarios'!G24 | F20: ='Scenarios'!H24 | G20: ='Scenarios'!I24
B21: vs price | C21: % | D21: ='Scenarios'!F25 | E21: ='Scenarios'!G25 | F21: ='Scenarios'!H25 | G21: ='Scenarios'!I25
B22: FY26E EPS, GAAP (with the fee) | C22: $ | D22: ='Scenarios'!F13 | E22: ='Scenarios'!G13 | F22: ='Scenarios'!H13 | G22: ='Scenarios'!I13
B23: FY26E EPS ex the fee | C23: $ | D23: ='Scenarios'!F14 | E23: ='Scenarios'!G14 | F23: ='Scenarios'!H14 | G23: ='Scenarios'!I14
B24: FY27E EPS | C24: $ | D24: ='Scenarios'!F15 | E24: ='Scenarios'!G15 | F24: ='Scenarios'!H15 | G24: ='Scenarios'!I15
B25: FY29E EPS | C25: $ | D25: ='Scenarios'!F16 | E25: ='Scenarios'!G16 | F25: ='Scenarios'!H16 | G25: ='Scenarios'!I16
B26: Exit P/E (NTM) | C26: x | D26: ='Scenarios'!F26 | E26: ='Scenarios'!G26 | F26: ='Scenarios'!H26
B27: Price at the end of 2028 | C27: $ | D27: ='Scenarios'!F27 | E27: ='Scenarios'!G27 | F27: ='Scenarios'!H27 | G27: ='Scenarios'!I27
B28: IRR to the end of 2028 | C28: % | D28: ='Scenarios'!F28 | E28: ='Scenarios'!G28 | F28: ='Scenarios'!H28 | G28: ='Scenarios'!I28
B29: Price at the end of 2029 | C29: $ | D29: ='Scenarios'!F29 | E29: ='Scenarios'!G29 | F29: ='Scenarios'!H29 | G29: ='Scenarios'!I29
B30: IRR to the end of 2029 | C30: % | D30: ='Scenarios'!F30 | E30: ='Scenarios'!G30 | F30: ='Scenarios'!H30 | G30: ='Scenarios'!I30
B31: Entry price for the hurdle IRR to exit 1 | C31: $ | D31: ='Scenarios'!F31 | E31: ='Scenarios'!G31 | F31: ='Scenarios'!H31 | G31: ='Scenarios'!I31
B32: FY29E operating margin | C32: % | D32: ='Scenarios'!F12 | E32: ='Scenarios'!G12 | F32: ='Scenarios'!H12
B33: FY28E advertising revenue | C33: $mm | D33: ='Scenarios'!F10 | E33: ='Scenarios'!G10 | F33: ='Scenarios'!H10
B34: FY27E share repurchases | C34: $mm | D34: ='Scenarios'!F20 | E34: ='Scenarios'!G20 | F34: ='Scenarios'!H20
B35: Reward / risk, 2028 price path: (bull - price) / (price - bear) | C35: x | D35: =(F27-'Drivers'!$D$7)/('Drivers'!$D$7-D27)
B36: Reward / risk, DCF: (bull - price) / (price - bear) | C36: x | D36: =(F20-'Drivers'!$D$7)/('Drivers'!$D$7-D20)
B38: ESTIMATES, ACTIVE SCENARIO | C38: =CHOOSE('Drivers'!$D$6,"Bear","Base","Bull")
B39: Fiscal year | D39: 2025 | E39: 2026 | F39: 2027 | G39: 2028 | H39: 2029 | I39: 2030
B40: Revenue | C40: $mm | D40: ='Model'!H16 | E40: ='Model'!I16 | F40: ='Model'!J16 | G40: ='Model'!K16 | H40: ='Model'!L16 | I40: ='Model'!M16
B41: y/y | C41: % | D41: ='Model'!H17 | E41: ='Model'!I17 | F41: ='Model'!J17 | G41: ='Model'!K17 | H41: ='Model'!L17 | I41: ='Model'!M17
B42: Advertising revenue (memo) | C42: $mm | D42: ='Model'!H18 | E42: ='Model'!I18 | F42: ='Model'!J18 | G42: ='Model'!K18 | H42: ='Model'!L18 | I42: ='Model'!M18
B43: Content amortization growth | C43: % | D43: ='Model'!H25 | E43: ='Model'!I25 | F43: ='Model'!J25 | G43: ='Model'!K25 | H43: ='Model'!L25 | I43: ='Model'!M25
B44: Operating income | C44: $mm | D44: ='Model'!H33 | E44: ='Model'!I33 | F44: ='Model'!J33 | G44: ='Model'!K33 | H44: ='Model'!L33 | I44: ='Model'!M33
B45: operating margin | C45: % | D45: ='Model'!H34 | E45: ='Model'!I34 | F45: ='Model'!J34 | G45: ='Model'!K34 | H45: ='Model'!L34 | I45: ='Model'!M34
B46: Net income | C46: $mm | D46: ='Model'!H42 | E46: ='Model'!I42 | F46: ='Model'!J42 | G46: ='Model'!K42 | H46: ='Model'!L42 | I46: ='Model'!M42
B47: Diluted EPS, GAAP | C47: $ | D47: ='Model'!H45 | E47: ='Model'!I45 | F47: ='Model'!J45 | G47: ='Model'!K45 | H47: ='Model'!L45 | I47: ='Model'!M45
B48: Diluted EPS ex one-offs | C48: $ | D48: ='Model'!H47 | E48: ='Model'!I47 | F48: ='Model'!J47 | G48: ='Model'!K47 | H48: ='Model'!L47 | I48: ='Model'!M47
B49: Free cash flow | C49: $mm | D49: ='Model'!H61 | E49: ='Model'!I61 | F49: ='Model'!J61 | G49: ='Model'!K61 | H49: ='Model'!L61 | I49: ='Model'!M61
B50: Share repurchases | C50: $mm | D50: ='Model'!H68 | E50: ='Model'!I68 | F50: ='Model'!J68 | G50: ='Model'!K68 | H50: ='Model'!L68 | I50: ='Model'!M68
B51: Diluted shares, weighted | C51: mm | D51: ='Model'!H44 | E51: ='Model'!I44 | F51: ='Model'!J44 | G51: ='Model'!K44 | H51: ='Model'!L44 | I51: ='Model'!M44
B52: Net debt, end of year | C52: $mm | D52: ='Model'!H71 | E52: ='Model'!I71 | F52: ='Model'!J71 | G52: ='Model'!K71 | H52: ='Model'!L71 | I52: ='Model'!M71
B54: GUIDANCE (2026-10-20) AND STREET (ACTIVE SCENARIO)
D55: Guide | F55: Model | G55: Check
B56: FY26 revenue | C56: $mm | D56: ='Drivers'!$D$95 | F56: ='Model'!I16 | G56: =IF(ABS(F56-D56)<=300,"near guide",IF(F56<D56,"below","above"))
B57: FY26 operating margin | C57: % | D57: ='Drivers'!$D$96 | F57: ='Model'!I34 | G57: =IF(ABS(F57-D57)<=0.004,"near guide",IF(F57<D57,"below","above"))
B58: FY26 free cash flow (with the fee) | C58: $mm | D58: ='Drivers'!$D$97 | F58: ='Model'!I61 | G58: =IF(ABS(F58-D58)<=600,"near guide",IF(F58<D58,"below","above"))
B59: FY26 advertising revenue | C59: $mm | D59: ='Drivers'!$D$98 | F59: ='Model'!I18 | G59: =IF(ABS(F59-D59)<=150,"near guide",IF(F59<D59,"below","above"))
B60: FY26 content amortization growth | C60: % | D60: ='Drivers'!$D$99 | F60: ='Model'!I25 | G60: =IF(ABS(F60-D60)<=0.01,"near guide",IF(F60<D60,"below","above"))
B61: 4Q26 revenue | C61: $mm | D61: ='Drivers'!$D$100 | F61: ='Quarterly'!L10 | G61: =IF(ABS(F61-D61)<=150,"near guide",IF(F61<D61,"below","above"))
B62: 4Q26 operating income | C62: $mm | D62: ='Drivers'!$D$101 | F62: ='Quarterly'!L19 | G62: =IF(ABS(F62-D62)<=150,"near guide",IF(F62<D62,"below","above"))
B63: 4Q26 diluted EPS | C63: $ | D63: ='Drivers'!$D$102 | F63: ='Quarterly'!L28 | G63: =IF(ABS(F63-D63)<=0.04,"near guide",IF(F63<D63,"below","above"))
D64: Street | F64: Model | G64: Model vs St.
B65: FY26E revenue | C65: $mm | D65: ='Drivers'!$D$103 | F65: ='Model'!I16 | G65: =F65/D65-1
B66: FY26E EPS, GAAP (Street includes the fee) | C66: $ | D66: ='Drivers'!$D$104 | F66: ='Model'!I45 | G66: =F66/D66-1
B67: FY27E revenue | C67: $mm | D67: ='Drivers'!$D$105 | F67: ='Model'!J16 | G67: =F67/D67-1
B68: FY27E EPS | C68: $ | D68: ='Drivers'!$D$106 | F68: ='Model'!J47 | G68: =F68/D68-1
B70: MODEL CHECKS
B71: History ties to reported operating income, net income, EPS | D71: =IF(SUM('Model'!F86:H86)<6,1,0)
B72: FY25 quarters sum to the annual revenue and net income | D72: =IF(ABS('Quarterly'!H10-'Model'!H16)+ABS('Quarterly'!H25-'Model'!H42)<6,1,0)
B73: Quarterly operating income and net income match the reported figures | D73: =IF(SUMPRODUCT(ABS('Quarterly'!D19:G19-'Quarterly'!D21:G21))+SUMPRODUCT(ABS('Quarterly'!I19:K19-'Quarterly'!I21:K21))+SUMPRODUCT(ABS('Quarterly'!D25:G25-'Quarterly'!D26:G26))+SUMPRODUCT(ABS('Quarterly'!I25:K25-'Quarterly'!I26:K26))<20,1,0)
B74: Probabilities sum to 100% | D74: =IF(ABS('Scenarios'!I7-1)<0.0001,1,0)
B75: WACC exceeds terminal growth in every scenario | D75: =IF('Drivers'!$D$29>MAX('Drivers'!F44:H44)+0.02,1,0)
B76: Active-scenario DCF equals its Scenarios chain | D76: =IF(ABS('Valuation'!D22-CHOOSE('Drivers'!$D$6,'Scenarios'!F24,'Scenarios'!G24,'Scenarios'!H24))<0.005,1,0)
B77: Cash never falls below the holding level in any scenario | D77: =IF(AND(MIN('Scenarios'!I103:R103-'Scenarios'!I98:R98)>-1,MIN('Scenarios'!I215:R215-'Scenarios'!I210:R210)>-1,MIN('Scenarios'!I327:R327-'Scenarios'!I322:R322)>-1),1,0)
B78: Share count falls every year in the base case | D78: =IF(MIN('Scenarios'!I219:R219)>0,1,0)
B79: FY26E GAAP EPS within 3% of the Street | D79: =IF(ABS('Model'!I45/'Drivers'!$D$104-1)<0.03,1,0)
B80: All checks | D80: =IF(SUM(D71:D79)=9,"OK","CHECK")

Sheet Drivers
B1: Netflix, Inc. | Drivers
B2: All inputs. FY25 10-K, Q3 2026 10-Q and shareholder letter (2026-10-20), market data 2026-10-23.
B3: Blue = input Black = formula Green = cross-sheet link $ in millions except per share; shares in millions (post-split)
B5: SCENARIO AND MARKET
B6: Active scenario (1 = Bear, 2 = Base, 3 = Bull) | C6: =CHOOSE(D6,"Bear","Base","Bull") | D6: 2 | E6: drives Model, Valuation and the Quarterly 4Q26E column; Scenarios and Summary values do not move
B7: Share price | C7: $ | D7: 66.29 | E7: Nasdaq close 2026-10-23; 52-week range $64.10 to $116.73; 10-for-1 split 2025-11-14
B8: Valuation date | D8: 46318 | E8: today
B9: Balance-sheet date used in the bridge | D9: 46295 | E9: Q3 2026 10-Q
B10: End of FY2026 | D10: 46387
B11: Exit date 1: end of 2028 | D11: 47118 | E11: multiple applied to 2029E EPS
B12: Exit date 2: end of 2029 | D12: 47483 | E12: multiple applied to 2030E EPS
B13: Diluted shares at 9/30/26 | C13: mm | D13: 4184 | E13: 4,106.3 basic on the 10-Q cover + ~78 dilutive (Q3 basic $0.89 vs diluted $0.87)
B14: Cash and short-term investments | C14: $mm | D14: 8223 | E14: 9/30/26: 8,194 + 29
B15: Gross debt (senior notes at par) | C15: $mm | D15: 15337 | E15: 9/30/26: $15,337mm par, carrying $15,132mm; EUR 4,700mm; $3B revolver and $3B CP undrawn
B16: Net debt | C16: $mm | D16: =D15-D14 | E16: the letter's non-GAAP net debt $7.1B
B17: WBD termination fee received, Q1 2026 (pre-tax) | C17: $mm | D17: 2800 | E17: paid by Paramount Skydance on WBD's behalf; booked in interest and other income
B18: Market capitalization | C18: $mm | D18: =D7*D13
B19: Enterprise value | C19: $mm | D19: =D18+D16
B21: COST OF CAPITAL
B22: Risk-free rate | C22: % | D22: 0.0499 | E22: UST 10Y, 2026-10-23
B23: Beta | C23: x | D23: 1.25 | E23: judgment: 5y regression 1.61 carries the 2022 drawdown; 2y nearer 1.1
B24: Equity risk premium | C24: % | D24: 0.05 | E24: judgment, desk convention
B25: Cost of equity | C25: % | D25: =D22+D23*D24
B26: Pre-tax cost of debt | C26: % | D26: 0.053 | E26: Aug 2026 notes: 5.25% 2036, 5.40% 2054
B27: Tax shield rate | C27: % | D27: 0.165
B28: Debt / (debt + market cap) | C28: % | D28: =D15/(D15+D18)
B29: WACC | C29: % | D29: =(1-D28)*D25+D28*D26*(1-D27)
B31: CASH AND CAPITAL CONVENTIONS
B32: Cash held, months of revenue | C32: mo | D32: 2 | E32: management's rule of thumb is about two months; 9/30/26 held 1.9 months
B33: Share creep before buybacks | C33: %/yr | D33: 0.004 | E33: equity-comp dilution
B34: 2026 blended repurchase price | C34: $ | D34: 82 | E34: 9M actual $85 (127mm shares, $10.8B); Q4 near the current price
B35: Repurchase price growth after 2026 | C35: %/yr | D35: 0.08 | E35: buybacks execute at today's price compounded
B36: Hurdle IRR for the entry price | C36: % | D36: 0.15 | E36: what the hold has to earn
B37: Sensitivity step, WACC | C37: % | D37: 0.0075
B38: Sensitivity step, terminal growth | C38: % | D38: 0.005
B39: Sensitivity step, exit P/E | C39: x | D39: 2
B41: SCENARIO SCALARS
D42: Active | F42: Bear | G42: Base | H42: Bull
B43: Probability | C43: % | D43: =CHOOSE($D$6,F43,G43,H43) | F43: 0.25 | G43: 0.5 | H43: 0.25 | I43: judgment
B44: Terminal growth | C44: % | D44: =CHOOSE($D$6,F44,G44,H44) | F44: 0.025 | G44: 0.03 | H44: 0.035 | I44: judgment
B45: Exit P/E (NTM) at both exit dates | C45: x | D45: =CHOOSE($D$6,F45,G45,H45) | F45: 14 | G45: 18 | H45: 22 | I45: today 17.6x FY27E Street EPS, 21.9x FY26E ex the fee; Earnings Desk 10-year trailing median 55x (growth was twice today's)
B47: FY2025 REVENUE BY REGION (TRUE-UP SURFACE)
B48: United States and Canada | C48: $mm | D48: 19957
B49: Europe, Middle East and Africa | C49: $mm | D49: 14515
B50: Latin America | C50: $mm | D50: 5358
B51: Asia-Pacific | C51: $mm | D51: 5354
B52: Total revenue | C52: $mm | D52: =SUM(D48:D51) | E52: ties to reported $45,183mm
B54: SHARED FORECAST VECTORS
B55: Fiscal year (calendar) | F55: 2023 | G55: 2024 | H55: 2025 | I55: 2026 | J55: 2027 | K55: 2028 | L55: 2029 | M55: 2030 | N55: 2031 | O55: 2032 | P55: 2033 | Q55: 2034 | R55: 2035
B56: Cash content spend / content amortization | C56: x | D56: FY26 guide ~1.1x; FY25 1.04x, FY24 1.06x | I56: 1.1 | J56: 1.1 | K56: 1.08 | L56: 1.08 | M56: 1.06 | N56: 1.06 | O56: 1.05 | P56: 1.05 | Q56: 1.05 | R56: 1.05
B57: Depreciation and amortization ex content, % of revenue | C57: % | D57: FY25 0.74% | I57: 0.0075 | J57: 0.0075 | K57: 0.0075 | L57: 0.0075 | M57: 0.0075 | N57: 0.0075 | O57: 0.0075 | P57: 0.0075 | Q57: 0.0075 | R57: 0.0075
B58: Stock-based compensation, % of revenue | C58: % | D58: 9M26 1.08%; FY25 0.82% | I58: 0.0105 | J58: 0.01 | K58: 0.0095 | L58: 0.009 | M58: 0.009 | N58: 0.009 | O58: 0.009 | P58: 0.009 | Q58: 0.009 | R58: 0.009
B59: Capital expenditures, % of revenue | C59: % | D59: 9M26 1.84%; FY25 1.52% | I59: 0.026 | J59: 0.0165 | K59: 0.016 | L59: 0.0155 | M59: 0.015 | N59: 0.015 | O59: 0.015 | P59: 0.015 | Q59: 0.015 | R59: 0.015
B60: Other operating cash items, % of revenue | C60: % | D60: content liabilities, deferred revenue, other: -1.4% to -2.6% FY23-25 | I60: -0.02 | J60: -0.015 | K60: -0.015 | L60: -0.015 | M60: -0.015 | N60: -0.015 | O60: -0.015 | P60: -0.015 | Q60: -0.015 | R60: -0.015
B61: Effective tax rate | C61: % | D61: 9M26 17.3%; FY25 13.7% | I61: 0.172 | J61: 0.165 | K61: 0.165 | L61: 0.165 | M61: 0.165 | N61: 0.165 | O61: 0.165 | P61: 0.165 | Q61: 0.165 | R61: 0.165
B62: Interest on gross debt | C62: % | D62: FY25 $777mm on ~$15B | I62: 0.053 | J62: 0.053 | K62: 0.053 | L62: 0.053 | M62: 0.053 | N62: 0.053 | O62: 0.053 | P62: 0.053 | Q62: 0.053 | R62: 0.053
B63: Interest income on beginning cash | C63: % | D63: net of FX remeasurement noise | I63: 0.025 | J63: 0.025 | K63: 0.025 | L63: 0.025 | M63: 0.025 | N63: 0.025 | O63: 0.025 | P63: 0.025 | Q63: 0.025 | R63: 0.025
B64: One-off items in other income (pre-tax) | C64: $mm | D64: 2026: the $2.8B WBD termination fee | I64: 2800 | J64: 0 | K64: 0 | L64: 0 | M64: 0 | N64: 0 | O64: 0 | P64: 0 | Q64: 0 | R64: 0
B65: Gross debt, end of year | C65: $mm | D65: maturities refinanced; $1B Nov-26 funded by the Aug-26 issue | I65: 15337 | J65: 15337 | K65: 15337 | L65: 15337 | M65: 15337 | N65: 15337 | O65: 15337 | P65: 15337 | Q65: 15337 | R65: 15337
B67: SCENARIO VECTORS
B68: Fiscal year (calendar) | F68: 2023 | G68: 2024 | H68: 2025 | I68: 2026 | J68: 2027 | K68: 2028 | L68: 2029 | M68: 2030 | N68: 2031 | O68: 2032 | P68: 2033 | Q68: 2034 | R68: 2035
B69: United States and Canada revenue growth | C69: % | D69: Bear | E69: FY25 +15.0% / +17.2% / +10.7% / +21.3%; 9M26 +11.5% / +14.1% / +18.9% / +15.8% | I69: 0.11 | J69: 0.06 | K69: 0.045 | L69: 0.04 | M69: 0.035 | N69: 0.03 | O69: 0.03 | P69: 0.025 | Q69: 0.025 | R69: 0.025
D70: Base | I70: 0.112 | J70: 0.09 | K70: 0.08 | L70: 0.07 | M70: 0.065 | N70: 0.06 | O70: 0.055 | P70: 0.05 | Q70: 0.045 | R70: 0.04
D71: Bull | I71: 0.114 | J71: 0.11 | K71: 0.1 | L71: 0.09 | M71: 0.08 | N71: 0.07 | O71: 0.065 | P71: 0.06 | Q71: 0.055 | R71: 0.05
B72: Europe, Middle East and Africa revenue growth | C72: % | D72: Bear | I72: 0.132 | J72: 0.08 | K72: 0.065 | L72: 0.055 | M72: 0.05 | N72: 0.04 | O72: 0.04 | P72: 0.035 | Q72: 0.035 | R72: 0.035
D73: Base | I73: 0.135 | J73: 0.115 | K73: 0.105 | L73: 0.095 | M73: 0.085 | N73: 0.08 | O73: 0.07 | P73: 0.065 | Q73: 0.06 | R73: 0.055
D74: Bull | I74: 0.138 | J74: 0.135 | K74: 0.125 | L74: 0.115 | M74: 0.105 | N74: 0.095 | O74: 0.085 | P74: 0.075 | Q74: 0.07 | R74: 0.065
B75: Latin America revenue growth | C75: % | D75: Bear | I75: 0.17 | J75: 0.09 | K75: 0.075 | L75: 0.065 | M75: 0.06 | N75: 0.05 | O75: 0.05 | P75: 0.045 | Q75: 0.04 | R75: 0.04
D76: Base | I76: 0.175 | J76: 0.13 | K76: 0.12 | L76: 0.11 | M76: 0.1 | N76: 0.09 | O76: 0.08 | P76: 0.07 | Q76: 0.065 | R76: 0.06
D77: Bull | I77: 0.18 | J77: 0.15 | K77: 0.14 | L77: 0.13 | M77: 0.12 | N77: 0.11 | O77: 0.1 | P77: 0.09 | Q77: 0.08 | R77: 0.07
B78: Asia-Pacific revenue growth | C78: % | D78: Bear | I78: 0.145 | J78: 0.09 | K78: 0.075 | L78: 0.065 | M78: 0.06 | N78: 0.05 | O78: 0.05 | P78: 0.045 | Q78: 0.04 | R78: 0.04
D79: Base | I79: 0.15 | J79: 0.13 | K79: 0.12 | L79: 0.11 | M79: 0.1 | N79: 0.09 | O79: 0.08 | P79: 0.07 | Q79: 0.065 | R79: 0.06
D80: Bull | I80: 0.155 | J80: 0.15 | K80: 0.14 | L80: 0.13 | M80: 0.12 | N80: 0.11 | O80: 0.1 | P80: 0.09 | Q80: 0.08 | R80: 0.07
B81: Advertising revenue (memo, inside the regional lines) | C81: $mm | D81: Bear | E81: FY25 ~1,500; FY26 guide ~2,700 (cut from ~3,000 on 2026-10-20) | I81: 2600 | J81: 3300 | K81: 4000 | L81: 4600 | M81: 5100 | N81: 5500 | O81: 5900 | P81: 6200 | Q81: 6500 | R81: 6800
D82: Base | I82: 2700 | J82: 3900 | K82: 5100 | L82: 6300 | M82: 7400 | N82: 8400 | O82: 9300 | P82: 10100 | Q82: 10800 | R82: 11500
D83: Bull | I83: 2750 | J83: 4300 | K83: 6000 | L83: 7800 | M83: 9500 | N83: 11000 | O83: 12400 | P83: 13600 | Q83: 14700 | R83: 15700
B84: Content amortization growth | C84: % | D84: Bear | E84: FY26 guide ~+10%; FY25 +7.3% | I84: 0.1 | J84: 0.09 | K84: 0.08 | L84: 0.07 | M84: 0.06 | N84: 0.05 | O84: 0.045 | P84: 0.04 | Q84: 0.035 | R84: 0.03
D85: Base | I85: 0.1 | J85: 0.085 | K85: 0.08 | L85: 0.075 | M85: 0.07 | N85: 0.065 | O85: 0.06 | P85: 0.055 | Q85: 0.05 | R85: 0.045
D86: Bull | I86: 0.1 | J86: 0.085 | K86: 0.08 | L86: 0.075 | M86: 0.07 | N86: 0.065 | O86: 0.06 | P86: 0.055 | Q86: 0.05 | R86: 0.045
B87: Other cost of revenues, % of revenue | C87: % | D87: Bear | E87: cost of revenues less amortization: 9M26 13.9%, FY25 15.2% | I87: 0.143 | J87: 0.145 | K87: 0.147 | L87: 0.148 | M87: 0.149 | N87: 0.15 | O87: 0.15 | P87: 0.15 | Q87: 0.15 | R87: 0.15
D88: Base | I88: 0.142 | J88: 0.14 | K88: 0.139 | L88: 0.138 | M88: 0.137 | N88: 0.136 | O88: 0.135 | P88: 0.135 | Q88: 0.135 | R88: 0.135
D89: Bull | I89: 0.141 | J89: 0.138 | K89: 0.135 | L89: 0.133 | M89: 0.131 | N89: 0.13 | O89: 0.129 | P89: 0.128 | Q89: 0.128 | R89: 0.128
B90: Operating expenses (S&M + T&D + G&A), % of revenue | C90: % | D90: Bear | E90: 9M26 18.8%; FY25 19.0%; Q4 carries the headcount charge | I90: 0.191 | J90: 0.193 | K90: 0.193 | L90: 0.192 | M90: 0.191 | N90: 0.19 | O90: 0.19 | P90: 0.19 | Q90: 0.19 | R90: 0.19
D91: Base | I91: 0.19 | J91: 0.183 | K91: 0.178 | L91: 0.174 | M91: 0.17 | N91: 0.167 | O91: 0.164 | P91: 0.162 | Q91: 0.16 | R91: 0.16
D92: Bull | I92: 0.189 | J92: 0.18 | K92: 0.172 | L92: 0.166 | M92: 0.161 | N92: 0.157 | O92: 0.154 | P92: 0.152 | Q92: 0.15 | R92: 0.149
B94: GUIDANCE (2026-10-20) AND STREET
B95: FY26 revenue | C95: $mm | D95: 51100 | E95: +13% (+12% F/X neutral)
B96: FY26 operating margin | C96: % | D96: 0.315 | E96: includes ~30 bp of headcount-reduction cost
B97: FY26 free cash flow | C97: $mm | D97: 12000 | E97: was ~12.5B; cut for a Q4 real-estate purchase
B98: FY26 advertising revenue | C98: $mm | D98: 2700 | E98: was ~3.0B
B99: FY26 content amortization growth | C99: % | D99: 0.1
B100: Q4 2026 revenue | C100: $mm | D100: 13442 | E100: +12% (+11% F/X neutral)
B101: Q4 2026 operating income | C101: $mm | D101: 3500 | E101: 26.0% margin incl. ~120 bp of headcount cost
B102: Q4 2026 diluted EPS | C102: $ | D102: 0.67 | E102: net income $2,787mm
B103: Street FY26 revenue | C103: $mm | D103: 51126 | E103: Yahoo 2026-10-23
B104: Street FY26 EPS (GAAP, includes the fee) | C104: $ | D104: 3.58 | E104: 35 analysts
B105: Street FY27 revenue | C105: $mm | D105: 56634
B106: Street FY27 EPS | C106: $ | D106: 3.76 | E106: range $3.56 to $3.98, 44 analysts
B107: Street price target, average | C107: $ | D107: 84.83 | E107: range $57 to $126; mean target $84.83, median $84 (Yahoo, 2026-10-23); more than 20 brokers cut targets after Q3 (LSEG via Reuters)

Sheet Quarterly
B1: Netflix, Inc. | Quarterly
B2: 2025 quarters, 1Q-3Q 2026A, and the 4Q26 the active scenario implies, against the Q4 guide.
B3: Blue = input Black = formula Green = cross-sheet link $ in millions except per share; shares in millions (post-split)
B5: Revenue | D5: 1Q25A | E5: 2Q25A | F5: 3Q25A | G5: 4Q25A | H5: FY25A | I5: 1Q26A | J5: 2Q26A | K5: 3Q26A | L5: 4Q26E | M5: FY26E | N5: y/y | O5: Q4 guide
B6: United States and Canada | C6: $mm | D6: 4617 | E6: 4929 | F6: 5072 | G6: 5339 | H6: =SUM(D6:G6) | I6: 5245 | J6: 5432 | K6: 5628 | L6: =M6-I6-J6-K6 | M6: ='Model'!I7 | N6: =M6/H6-1
B7: Europe, Middle East and Africa | C7: $mm | D7: 3405 | E7: 3538 | F7: 3699 | G7: 3873 | H7: =SUM(D7:G7) | I7: 3998 | J7: 4034 | K7: 4107 | L7: =M7-I7-J7-K7 | M7: ='Model'!I9 | N7: =M7/H7-1
B8: Latin America | C8: $mm | D8: 1262 | E8: 1307 | F8: 1371 | G8: 1418 | H8: =SUM(D8:G8) | I8: 1497 | J8: 1584 | K8: 1603 | L8: =M8-I8-J8-K8 | M8: ='Model'!I11 | N8: =M8/H8-1
B9: Asia-Pacific | C9: $mm | D9: 1259 | E9: 1305 | F9: 1369 | G9: 1421 | H9: =SUM(D9:G9) | I9: 1509 | J9: 1510 | K9: 1537 | L9: =M9-I9-J9-K9 | M9: ='Model'!I13 | N9: =M9/H9-1
B10: Total revenue | C10: $mm | D10: =D6+D7+D8+D9 | E10: =E6+E7+E8+E9 | F10: =F6+F7+F8+F9 | G10: =G6+G7+G8+G9 | H10: =H6+H7+H8+H9 | I10: =I6+I7+I8+I9 | J10: =J6+J7+J8+J9 | K10: =K6+K7+K8+K9 | L10: =M10-I10-J10-K10 | M10: ='Model'!I16 | N10: =M10/H10-1 | O10: ='Drivers'!$D$100
B11: y/y | C11: % | I11: =I10/D10-1 | J11: =J10/E10-1 | K11: =K10/F10-1 | L11: =L10/G10-1 | M11: =M10/H10-1 | O11: =O10/G10-1
B13: INCOME STATEMENT
B14: Cost of revenues (incl. content amortization) | C14: $mm | D14: 5263 | E14: 5325 | F14: 6164 | G14: 6523 | H14: =SUM(D14:G14) | I14: 5888 | J14: 6037 | K14: 6079 | L14: =M14-I14-J14-K14 | M14: ='Model'!I24+'Model'!I27 | N14: =M14/H14-1
B15: Sales and marketing | C15: $mm | D15: 688 | E15: 713 | F15: 786 | G15: 1114 | H15: =SUM(D15:G15) | I15: 842 | J15: 824 | K15: 837
B16: Technology and development | C16: $mm | D16: 823 | E16: 825 | F16: 854 | G16: 890 | H16: =SUM(D16:G16) | I16: 960 | J16: 1008 | K16: 1033
B17: General and administrative | C17: $mm | D17: 421 | E17: 441 | F17: 458 | G17: 568 | H17: =SUM(D17:G17) | I17: 603 | J17: 499 | K17: 466
B18: Operating expenses | C18: $mm | D18: =D15+D16+D17 | E18: =E15+E16+E17 | F18: =F15+F16+F17 | G18: =G15+G16+G17 | H18: =H15+H16+H17 | I18: =I15+I16+I17 | J18: =J15+J16+J17 | K18: =K15+K16+K17 | L18: =M18-I18-J18-K18 | M18: ='Model'!I31 | N18: =M18/H18-1
B19: Operating income | C19: $mm | D19: =D10-D14-D18 | E19: =E10-E14-E18 | F19: =F10-F14-F18 | G19: =G10-G14-G18 | H19: =H10-H14-H18 | I19: =I10-I14-I18 | J19: =J10-J14-J18 | K19: =K10-K14-K18 | L19: =M19-I19-J19-K19 | M19: ='Model'!I33 | N19: =M19/H19-1 | O19: ='Drivers'!$D$101
B20: operating margin | C20: % | D20: =D19/D10 | E20: =E19/E10 | F20: =F19/F10 | G20: =G19/G10 | H20: =H19/H10 | I20: =I19/I10 | J20: =J19/J10 | K20: =K19/K10 | ... M20: =M19/M10 | O20: =O19/O10
B21: Operating income, reported (memo) | C21: $mm | D21: 3347 | E21: 3775 | F21: 3248 | G21: 2957 | H21: =SUM(D21:G21) | I21: 3957 | J21: 4193 | K21: 4459
B22: Interest and other, net (1Q26 includes the $2.8B fee) | C22: $mm | D22: -133 | E22: -143 | F22: -139 | G22: -189 | H22: =SUM(D22:G22) | I22: 2590 | J22: -124 | K22: -142 | L22: =M22-I22-J22-K22 | M22: ='Model'!I36+'Model'!I37 | N22: =M22/H22-1
B23: Income before income taxes | C23: $mm | D23: =D19+D22 | E23: =E19+E22 | F23: =F19+F22 | G23: =G19+G22 | H23: =H19+H22 | I23: =I19+I22 | J23: =J19+J22 | K23: =K19+K22 | L23: =M23-I23-J23-K23 | M23: =M19+M22 | N23: =M23/H23-1
B24: Provision for income taxes | C24: $mm | D24: 323 | E24: 506 | F24: 562 | G24: 349 | H24: =SUM(D24:G24) | I24: 1264 | J24: 667 | K24: 653 | L24: =M24-I24-J24-K24 | M24: ='Model'!I40 | N24: =M24/H24-1
B25: Net income | C25: $mm | D25: =D23-D24 | E25: =E23-E24 | F25: =F23-F24 | G25: =G23-G24 | H25: =H23-H24 | I25: =I23-I24 | J25: =J23-J24 | K25: =K23-K24 | L25: =M25-I25-J25-K25 | M25: =M23-M24 | N25: =M25/H25-1 | O25: 2787
B26: Net income, reported (memo) | C26: $mm | D26: 2890 | E26: 3125 | F26: 2547 | G26: 2419 | H26: =SUM(D26:G26) | I26: 5283 | J26: 3401 | K26: 3664
B27: Diluted shares | C27: mm | D27: 4369.6 | E27: 4348.8 | F27: 4340.4 | G27: 4330 | H27: 4344 | I27: 4298.4 | J27: 4261.3 | K27: 4195.1 | L27: ='Model'!I73 | M27: ='Model'!I44
B28: Diluted EPS, GAAP | C28: $ | D28: =D25/D27 | E28: =E25/E27 | F28: =F25/F27 | G28: =G25/G27 | H28: =H25/H27 | I28: =I25/I27 | J28: =J25/J27 | K28: =K25/K27 | ... M28: =M25/M27 | N28: =M28/H28-1 | O28: ='Drivers'!$D$102
B29: Diluted EPS, reported (memo) | C29: $ | D29: 0.66 | E29: 0.72 | F29: 0.59 | G29: 0.56 | H29: 2.53 | I29: 1.23 | J29: 0.8 | K29: 0.87
B31: CASH FLOW
B32: Free cash flow (company definition) | C32: $mm | D32: 2661 | E32: 2273 | F32: 2660 | G32: 1867 | H32: =SUM(D32:G32) | I32: 5094 | J32: 1525 | K32: 2884 | L32: =M32-I32-J32-K32 | M32: ='Model'!I61 | N32: =M32/H32-1 | O32: ='Drivers'!$D$97-I32-J32-K32 | P32: Q4 guide column = FY guide $12.0B less 9M actual
B33: Share repurchases (cash paid) | C33: $mm | D33: 3536 | E33: 1654 | F33: 1857 | G33: 2080 | H33: =SUM(D33:G33) | I33: 1271 | J33: 4714 | K33: 4797 | L33: =M33-I33-J33-K33 | M33: =-'Model'!I68 | N33: =M33/H33-1
B34: Cash content spend / amortization, nine months | C34: x | H34: =12039/11658 | K34: =14934/12765 | M34: ='Model'!I54 | P34: 9M26 additions 14,934 / amortization 12,765; FY guide ~1.1x

Sheet Model
B1: Netflix, Inc. | Model
B2: ="Active scenario: "&CHOOSE('Drivers'!$D$6,"Bear","Base","Bull")&". FY2023A to FY2025A reported, FY2026E to FY2035E forecast. Calendar years."
B3: Blue = input Black = formula Green = cross-sheet link $ in millions except per share; shares in millions (post-split)
B5: REVENUE | ACTIVE SCENARIO
B6: Fiscal year (calendar) | F6: 2023 | G6: 2024 | H6: 2025 | I6: 2026 | J6: 2027 | K6: 2028 | L6: 2029 | M6: 2030 | N6: 2031 | O6: 2032 | P6: 2033 | Q6: 2034 | R6: 2035
B7: United States and Canada | C7: $mm | F7: 14874 | G7: 17359 | H7: ='Drivers'!$D$48 | I7: =H7*(1+I8) | J7: =I7*(1+J8) | K7: =J7*(1+K8) | L7: =K7*(1+L8) | M7: =L7*(1+M8) | N7: =M7*(1+N8) | O7: =N7*(1+O8) | P7: =O7*(1+P8) | ... R7: =Q7*(1+R8)
B8: y/y | C8: % | G8: =G7/F7-1 | H8: =H7/G7-1 | I8: =CHOOSE('Drivers'!$D$6,'Drivers'!I$69,'Drivers'!I$70,'Drivers'!I$71) | J8: =CHOOSE('Drivers'!$D$6,'Drivers'!J$69,'Drivers'!J$70,'Drivers'!J$71) | K8: =CHOOSE('Drivers'!$D$6,'Drivers'!K$69,'Drivers'!K$70,'Drivers'!K$71) | L8: =CHOOSE('Drivers'!$D$6,'Drivers'!L$69,'Drivers'!L$70,'Drivers'!L$71) | M8: =CHOOSE('Drivers'!$D$6,'Drivers'!M$69,'Drivers'!M$70,'Drivers'!M$71) | N8: =CHOOSE('Drivers'!$D$6,'Drivers'!N$69,'Drivers'!N$70,'Drivers'!N$71) | O8: =CHOOSE('Drivers'!$D$6,'Drivers'!O$69,'Drivers'!O$70,'Drivers'!O$71) | P8: =CHOOSE('Drivers'!$D$6,'Drivers'!P$69,'Drivers'!P$70,'Drivers'!P$71) | ... R8: =CHOOSE('Drivers'!$D$6,'Drivers'!R$69,'Drivers'!R$70,'Drivers'!R$71)
B9: Europe, Middle East and Africa | C9: $mm | F9: 10556 | G9: 12387 | H9: ='Drivers'!$D$49 | I9: =H9*(1+I10) | J9: =I9*(1+J10) | K9: =J9*(1+K10) | L9: =K9*(1+L10) | M9: =L9*(1+M10) | N9: =M9*(1+N10) | O9: =N9*(1+O10) | P9: =O9*(1+P10) | ... R9: =Q9*(1+R10)
B10: y/y | C10: % | G10: =G9/F9-1 | H10: =H9/G9-1 | I10: =CHOOSE('Drivers'!$D$6,'Drivers'!I$72,'Drivers'!I$73,'Drivers'!I$74) | J10: =CHOOSE('Drivers'!$D$6,'Drivers'!J$72,'Drivers'!J$73,'Drivers'!J$74) | K10: =CHOOSE('Drivers'!$D$6,'Drivers'!K$72,'Drivers'!K$73,'Drivers'!K$74) | L10: =CHOOSE('Drivers'!$D$6,'Drivers'!L$72,'Drivers'!L$73,'Drivers'!L$74) | M10: =CHOOSE('Drivers'!$D$6,'Drivers'!M$72,'Drivers'!M$73,'Drivers'!M$74) | N10: =CHOOSE('Drivers'!$D$6,'Drivers'!N$72,'Drivers'!N$73,'Drivers'!N$74) | O10: =CHOOSE('Drivers'!$D$6,'Drivers'!O$72,'Drivers'!O$73,'Drivers'!O$74) | P10: =CHOOSE('Drivers'!$D$6,'Drivers'!P$72,'Drivers'!P$73,'Drivers'!P$74) | ... R10: =CHOOSE('Drivers'!$D$6,'Drivers'!R$72,'Drivers'!R$73,'Drivers'!R$74)
B11: Latin America | C11: $mm | F11: 4446 | G11: 4840 | H11: ='Drivers'!$D$50 | I11: =H11*(1+I12) | J11: =I11*(1+J12) | K11: =J11*(1+K12) | L11: =K11*(1+L12) | M11: =L11*(1+M12) | N11: =M11*(1+N12) | O11: =N11*(1+O12) | P11: =O11*(1+P12) | ... R11: =Q11*(1+R12)
B12: y/y | C12: % | G12: =G11/F11-1 | H12: =H11/G11-1 | I12: =CHOOSE('Drivers'!$D$6,'Drivers'!I$75,'Drivers'!I$76,'Drivers'!I$77) | J12: =CHOOSE('Drivers'!$D$6,'Drivers'!J$75,'Drivers'!J$76,'Drivers'!J$77) | K12: =CHOOSE('Drivers'!$D$6,'Drivers'!K$75,'Drivers'!K$76,'Drivers'!K$77) | L12: =CHOOSE('Drivers'!$D$6,'Drivers'!L$75,'Drivers'!L$76,'Drivers'!L$77) | M12: =CHOOSE('Drivers'!$D$6,'Drivers'!M$75,'Drivers'!M$76,'Drivers'!M$77) | N12: =CHOOSE('Drivers'!$D$6,'Drivers'!N$75,'Drivers'!N$76,'Drivers'!N$77) | O12: =CHOOSE('Drivers'!$D$6,'Drivers'!O$75,'Drivers'!O$76,'Drivers'!O$77) | P12: =CHOOSE('Drivers'!$D$6,'Drivers'!P$75,'Drivers'!P$76,'Drivers'!P$77) | ... R12: =CHOOSE('Drivers'!$D$6,'Drivers'!R$75,'Drivers'!R$76,'Drivers'!R$77)
B13: Asia-Pacific | C13: $mm | F13: 3764 | G13: 4415 | H13: ='Drivers'!$D$51 | I13: =H13*(1+I14) | J13: =I13*(1+J14) | K13: =J13*(1+K14) | L13: =K13*(1+L14) | M13: =L13*(1+M14) | N13: =M13*(1+N14) | O13: =N13*(1+O14) | P13: =O13*(1+P14) | ... R13: =Q13*(1+R14)
B14: y/y | C14: % | G14: =G13/F13-1 | H14: =H13/G13-1 | I14: =CHOOSE('Drivers'!$D$6,'Drivers'!I$78,'Drivers'!I$79,'Drivers'!I$80) | J14: =CHOOSE('Drivers'!$D$6,'Drivers'!J$78,'Drivers'!J$79,'Drivers'!J$80) | K14: =CHOOSE('Drivers'!$D$6,'Drivers'!K$78,'Drivers'!K$79,'Drivers'!K$80) | L14: =CHOOSE('Drivers'!$D$6,'Drivers'!L$78,'Drivers'!L$79,'Drivers'!L$80) | M14: =CHOOSE('Drivers'!$D$6,'Drivers'!M$78,'Drivers'!M$79,'Drivers'!M$80) | N14: =CHOOSE('Drivers'!$D$6,'Drivers'!N$78,'Drivers'!N$79,'Drivers'!N$80) | O14: =CHOOSE('Drivers'!$D$6,'Drivers'!O$78,'Drivers'!O$79,'Drivers'!O$80) | P14: =CHOOSE('Drivers'!$D$6,'Drivers'!P$78,'Drivers'!P$79,'Drivers'!P$80) | ... R14: =CHOOSE('Drivers'!$D$6,'Drivers'!R$78,'Drivers'!R$79,'Drivers'!R$80)
B15: DVD (wound down 2023) | C15: $mm | F15: 83 | G15: 0 | H15: 0 | I15: =0 | J15: =0 | K15: =0 | L15: =0 | M15: =0 | N15: =0 | O15: =0 | P15: =0 | ... R15: =0
B16: Total revenue | C16: $mm | F16: =F7+F9+F11+F13+F15 | G16: =G7+G9+G11+G13+G15 | H16: =H7+H9+H11+H13+H15 | I16: =I7+I9+I11+I13+I15 | J16: =J7+J9+J11+J13+J15 | K16: =K7+K9+K11+K13+K15 | L16: =L7+L9+L11+L13+L15 | M16: =M7+M9+M11+M13+M15 | ... R16: =R7+R9+R11+R13+R15
B17: y/y | C17: % | G17: =G16/F16-1 | H17: =H16/G16-1 | I17: =I16/H16-1 | J17: =J16/I16-1 | K17: =K16/J16-1 | L17: =L16/K16-1 | M17: =M16/L16-1 | N17: =N16/M16-1 | ... R17: =R16/Q16-1
B18: of which advertising (memo) | C18: $mm | G18: 600 | H18: 1500 | I18: =CHOOSE('Drivers'!$D$6,'Drivers'!I$81,'Drivers'!I$82,'Drivers'!I$83) | J18: =CHOOSE('Drivers'!$D$6,'Drivers'!J$81,'Drivers'!J$82,'Drivers'!J$83) | K18: =CHOOSE('Drivers'!$D$6,'Drivers'!K$81,'Drivers'!K$82,'Drivers'!K$83) | L18: =CHOOSE('Drivers'!$D$6,'Drivers'!L$81,'Drivers'!L$82,'Drivers'!L$83) | M18: =CHOOSE('Drivers'!$D$6,'Drivers'!M$81,'Drivers'!M$82,'Drivers'!M$83) | N18: =CHOOSE('Drivers'!$D$6,'Drivers'!N$81,'Drivers'!N$82,'Drivers'!N$83) | O18: =CHOOSE('Drivers'!$D$6,'Drivers'!O$81,'Drivers'!O$82,'Drivers'!O$83) | P18: =CHOOSE('Drivers'!$D$6,'Drivers'!P$81,'Drivers'!P$82,'Drivers'!P$83) | ... R18: =CHOOSE('Drivers'!$D$6,'Drivers'!R$81,'Drivers'!R$82,'Drivers'!R$83)
B19: advertising, % of revenue | C19: % | G19: =G18/G16 | H19: =H18/H16 | I19: =I18/I16 | J19: =J18/J16 | K19: =K18/K16 | L19: =L18/L16 | M19: =M18/M16 | N19: =N18/N16 | ... R19: =R18/R16
B20: subscription and other (memo) | C20: $mm | G20: =G16-G18 | H20: =H16-H18 | I20: =I16-I18 | J20: =J16-J18 | K20: =K16-K18 | L20: =L16-L18 | M20: =M16-M18 | N20: =N16-N18 | ... R20: =R16-R18
B21: y/y | C21: % | H21: =H20/G20-1 | I21: =I20/H20-1 | J21: =J20/I20-1 | K21: =K20/J20-1 | L21: =L20/K20-1 | M21: =M20/L20-1 | N21: =N20/M20-1 | O21: =O20/N20-1 | ... R21: =R20/Q20-1
B23: INCOME STATEMENT
B24: Content amortization | C24: $mm | F24: 14197 | G24: 15302 | H24: 16422 | I24: =H24*(1+I25) | J24: =I24*(1+J25) | K24: =J24*(1+K25) | L24: =K24*(1+L25) | M24: =L24*(1+M25) | N24: =M24*(1+N25) | O24: =N24*(1+O25) | P24: =O24*(1+P25) | ... R24: =Q24*(1+R25)
B25: y/y | C25: % | G25: =G24/F24-1 | H25: =H24/G24-1 | I25: =CHOOSE('Drivers'!$D$6,'Drivers'!I$84,'Drivers'!I$85,'Drivers'!I$86) | J25: =CHOOSE('Drivers'!$D$6,'Drivers'!J$84,'Drivers'!J$85,'Drivers'!J$86) | K25: =CHOOSE('Drivers'!$D$6,'Drivers'!K$84,'Drivers'!K$85,'Drivers'!K$86) | L25: =CHOOSE('Drivers'!$D$6,'Drivers'!L$84,'Drivers'!L$85,'Drivers'!L$86) | M25: =CHOOSE('Drivers'!$D$6,'Drivers'!M$84,'Drivers'!M$85,'Drivers'!M$86) | N25: =CHOOSE('Drivers'!$D$6,'Drivers'!N$84,'Drivers'!N$85,'Drivers'!N$86) | O25: =CHOOSE('Drivers'!$D$6,'Drivers'!O$84,'Drivers'!O$85,'Drivers'!O$86) | P25: =CHOOSE('Drivers'!$D$6,'Drivers'!P$84,'Drivers'!P$85,'Drivers'!P$86) | ... R25: =CHOOSE('Drivers'!$D$6,'Drivers'!R$84,'Drivers'!R$85,'Drivers'!R$86)
B26: % of revenue | C26: % | F26: =F24/F16 | G26: =G24/G16 | H26: =H24/H16 | I26: =I24/I16 | J26: =J24/J16 | K26: =K24/K16 | L26: =L24/L16 | M26: =M24/M16 | ... R26: =R24/R16
B27: Other cost of revenues | C27: $mm | F27: =19715-14197 | G27: =21038-15302 | H27: =23275-16422 | I27: =I16*I28 | J27: =J16*J28 | K27: =K16*K28 | L27: =L16*L28 | M27: =M16*M28 | N27: =N16*N28 | O27: =O16*O28 | P27: =P16*P28 | ... R27: =R16*R28
B28: % of revenue | C28: % | F28: =F27/F16 | G28: =G27/G16 | H28: =H27/H16 | I28: =CHOOSE('Drivers'!$D$6,'Drivers'!I$87,'Drivers'!I$88,'Drivers'!I$89) | J28: =CHOOSE('Drivers'!$D$6,'Drivers'!J$87,'Drivers'!J$88,'Drivers'!J$89) | K28: =CHOOSE('Drivers'!$D$6,'Drivers'!K$87,'Drivers'!K$88,'Drivers'!K$89) | L28: =CHOOSE('Drivers'!$D$6,'Drivers'!L$87,'Drivers'!L$88,'Drivers'!L$89) | M28: =CHOOSE('Drivers'!$D$6,'Drivers'!M$87,'Drivers'!M$88,'Drivers'!M$89) | N28: =CHOOSE('Drivers'!$D$6,'Drivers'!N$87,'Drivers'!N$88,'Drivers'!N$89) | O28: =CHOOSE('Drivers'!$D$6,'Drivers'!O$87,'Drivers'!O$88,'Drivers'!O$89) | P28: =CHOOSE('Drivers'!$D$6,'Drivers'!P$87,'Drivers'!P$88,'Drivers'!P$89) | ... R28: =CHOOSE('Drivers'!$D$6,'Drivers'!R$87,'Drivers'!R$88,'Drivers'!R$89)
B29: Gross profit | C29: $mm | F29: =F16-F24-F27 | G29: =G16-G24-G27 | H29: =H16-H24-H27 | I29: =I16-I24-I27 | J29: =J16-J24-J27 | K29: =K16-K24-K27 | L29: =L16-L24-L27 | M29: =M16-M24-M27 | ... R29: =R16-R24-R27
B30: gross margin | C30: % | F30: =F29/F16 | G30: =G29/G16 | H30: =H29/H16 | I30: =I29/I16 | J30: =J29/J16 | K30: =K29/K16 | L30: =L29/L16 | M30: =M29/M16 | ... R30: =R29/R16
B31: Operating expenses (sales and marketing, technology, G&A) | C31: $mm | F31: =2658+2676+1720 | G31: =2918+2925+1702 | H31: =3301+3391+1888 | I31: =I16*I32 | J31: =J16*J32 | K31: =K16*K32 | L31: =L16*L32 | M31: =M16*M32 | N31: =N16*N32 | O31: =O16*O32 | P31: =P16*P32 | ... R31: =R16*R32
B32: % of revenue | C32: % | F32: =F31/F16 | G32: =G31/G16 | H32: =H31/H16 | I32: =CHOOSE('Drivers'!$D$6,'Drivers'!I$90,'Drivers'!I$91,'Drivers'!I$92) | J32: =CHOOSE('Drivers'!$D$6,'Drivers'!J$90,'Drivers'!J$91,'Drivers'!J$92) | K32: =CHOOSE('Drivers'!$D$6,'Drivers'!K$90,'Drivers'!K$91,'Drivers'!K$92) | L32: =CHOOSE('Drivers'!$D$6,'Drivers'!L$90,'Drivers'!L$91,'Drivers'!L$92) | M32: =CHOOSE('Drivers'!$D$6,'Drivers'!M$90,'Drivers'!M$91,'Drivers'!M$92) | N32: =CHOOSE('Drivers'!$D$6,'Drivers'!N$90,'Drivers'!N$91,'Drivers'!N$92) | O32: =CHOOSE('Drivers'!$D$6,'Drivers'!O$90,'Drivers'!O$91,'Drivers'!O$92) | P32: =CHOOSE('Drivers'!$D$6,'Drivers'!P$90,'Drivers'!P$91,'Drivers'!P$92) | ... R32: =CHOOSE('Drivers'!$D$6,'Drivers'!R$90,'Drivers'!R$91,'Drivers'!R$92)
B33: Operating income | C33: $mm | F33: =F29-F31 | G33: =G29-G31 | H33: =H29-H31 | I33: =I29-I31 | J33: =J29-J31 | K33: =K29-K31 | L33: =L29-L31 | M33: =M29-M31 | ... R33: =R29-R31
B34: operating margin | C34: % | F34: =F33/F16 | G34: =G33/G16 | H34: =H33/H16 | I34: =I33/I16 | J34: =J33/J16 | K34: =K33/K16 | L34: =L33/L16 | M34: =M33/M16 | ... R34: =R33/R16
B35: y/y | C35: % | G35: =G33/F33-1 | H35: =H33/G33-1 | I35: =I33/H33-1 | J35: =J33/I33-1 | K35: =K33/J33-1 | L35: =L33/K33-1 | M35: =M33/L33-1 | N35: =N33/M33-1 | ... R35: =R33/Q33-1
B36: Interest expense | C36: $mm | F36: -700 | G36: -719 | H36: -777 | I36: =-H66*'Drivers'!I$62 | J36: =-I66*'Drivers'!J$62 | K36: =-J66*'Drivers'!K$62 | L36: =-K66*'Drivers'!L$62 | M36: =-L66*'Drivers'!M$62 | N36: =-M66*'Drivers'!N$62 | O36: =-N66*'Drivers'!O$62 | P36: =-O66*'Drivers'!P$62 | ... R36: =-Q66*'Drivers'!R$62
B37: Interest and other income (expense) | C37: $mm | F37: -49 | G37: 267 | H37: 172 | I37: =I64*'Drivers'!I$63+I38 | J37: =J64*'Drivers'!J$63+J38 | K37: =K64*'Drivers'!K$63+K38 | L37: =L64*'Drivers'!L$63+L38 | M37: =M64*'Drivers'!M$63+M38 | N37: =N64*'Drivers'!N$63+N38 | O37: =O64*'Drivers'!O$63+O38 | P37: =P64*'Drivers'!P$63+P38 | ... R37: =R64*'Drivers'!R$63+R38
B38: of which one-off (WBD termination fee) | C38: $mm | F38: 0 | G38: 0 | H38: 0 | I38: ='Drivers'!I$64 | J38: ='Drivers'!J$64 | K38: ='Drivers'!K$64 | L38: ='Drivers'!L$64 | M38: ='Drivers'!M$64 | N38: ='Drivers'!N$64 | O38: ='Drivers'!O$64 | P38: ='Drivers'!P$64 | ... R38: ='Drivers'!R$64
B39: Income before income taxes | C39: $mm | F39: =F33+F36+F37 | G39: =G33+G36+G37 | H39: =H33+H36+H37 | I39: =I33+I36+I37 | J39: =J33+J36+J37 | K39: =K33+K36+K37 | L39: =L33+L36+L37 | M39: =M33+M36+M37 | ... R39: =R33+R36+R37
B40: Provision for income taxes | C40: $mm | F40: 797 | G40: 1254 | H40: 1741 | I40: =I39*I41 | J40: =J39*J41 | K40: =K39*K41 | L40: =L39*L41 | M40: =M39*M41 | N40: =N39*N41 | O40: =O39*O41 | P40: =P39*P41 | ... R40: =R39*R41
B41: effective tax rate | C41: % | F41: =F40/F39 | G41: =G40/G39 | H41: =H40/H39 | I41: ='Drivers'!I$61 | J41: ='Drivers'!J$61 | K41: ='Drivers'!K$61 | L41: ='Drivers'!L$61 | M41: ='Drivers'!M$61 | N41: ='Drivers'!N$61 | O41: ='Drivers'!O$61 | P41: ='Drivers'!P$61 | ... R41: ='Drivers'!R$61
B42: Net income | C42: $mm | F42: =F39-F40 | G42: =G39-G40 | H42: =H39-H40 | I42: =I39-I40 | J42: =J39-J40 | K42: =K39-K40 | L42: =L39-L40 | M42: =M39-M40 | ... R42: =R39-R40
B43: net margin | C43: % | F43: =F42/F16 | G43: =G42/G16 | H43: =H42/H16 | I43: =I42/I16 | J43: =J42/J16 | K43: =K42/K16 | L43: =L42/L16 | M43: =M42/M16 | ... R43: =R42/R16
B44: Diluted shares, weighted average | C44: mm | F44: 4495 | G44: 4393 | H44: 4344 | I44: =(H73+I73)/2 | J44: =(I73+J73)/2 | K44: =(J73+K73)/2 | L44: =(K73+L73)/2 | M44: =(L73+M73)/2 | N44: =(M73+N73)/2 | O44: =(N73+O73)/2 | P44: =(O73+P73)/2 | ... R44: =(Q73+R73)/2
B45: Diluted EPS, GAAP | C45: $ | F45: =F42/F44 | G45: =G42/G44 | H45: =H42/H44 | I45: =I42/I44 | J45: =J42/J44 | K45: =K42/K44 | L45: =L42/L44 | M45: =M42/M44 | ... R45: =R42/R44
B46: y/y | C46: % | G46: =G45/F45-1 | H46: =H45/G45-1 | I46: =I45/H45-1 | J46: =J45/I45-1 | K46: =K45/J45-1 | L46: =L45/K45-1 | M46: =M45/L45-1 | N46: =N45/M45-1 | ... R46: =R45/Q45-1
B47: Diluted EPS ex one-offs | C47: $ | F47: =(F39-F38)*(1-F41)/F44 | G47: =(G39-G38)*(1-G41)/G44 | H47: =(H39-H38)*(1-H41)/H44 | I47: =(I39-I38)*(1-I41)/I44 | J47: =(J39-J38)*(1-J41)/J44 | K47: =(K39-K38)*(1-K41)/K44 | L47: =(L39-L38)*(1-L41)/L44 | M47: =(M39-M38)*(1-M41)/M44 | ... R47: =(R39-R38)*(1-R41)/R44
B48: y/y | C48: % | G48: =G47/F47-1 | H48: =H47/G47-1 | I48: =I47/H47-1 | J48: =J47/I47-1 | K48: =K47/J47-1 | L48: =L47/K47-1 | M48: =M47/L47-1 | N48: =N47/M47-1 | ... R48: =R47/Q47-1
B50: CASH FLOW, BUYBACKS AND NET DEBT
B51: NOPAT (operating income after tax) | C51: $mm | I51: =I33*(1-I41) | J51: =J33*(1-J41) | K51: =K33*(1-K41) | L51: =L33*(1-L41) | M51: =M33*(1-M41) | N51: =N33*(1-N41) | O51: =O33*(1-O41) | P51: =P33*(1-P41) | ... R51: =R33*(1-R41)
B52: Plus: content amortization | C52: $mm | F52: 14197 | G52: 15302 | H52: 16422 | I52: =I24 | J52: =J24 | K52: =K24 | L52: =L24 | M52: =M24 | N52: =N24 | O52: =O24 | P52: =P24 | ... R52: =R24
B53: Less: cash content spend | C53: $mm | F53: -12555 | G53: -16224 | H53: -17097 | I53: =-I24*'Drivers'!I$56 | J53: =-J24*'Drivers'!J$56 | K53: =-K24*'Drivers'!K$56 | L53: =-L24*'Drivers'!L$56 | M53: =-M24*'Drivers'!M$56 | N53: =-N24*'Drivers'!N$56 | O53: =-O24*'Drivers'!O$56 | P53: =-P24*'Drivers'!P$56 | ... R53: =-R24*'Drivers'!R$56
B54: cash content spend / amortization | C54: x | F54: =-F53/F52 | G54: =-G53/G52 | H54: =-H53/H52 | I54: =-I53/I52 | J54: =-J53/J52 | K54: =-K53/K52 | L54: =-L53/L52 | M54: =-M53/M52 | ... R54: =-R53/R52
B55: Plus: depreciation and amortization ex content | C55: $mm | F55: 357 | G55: 329 | H55: 333 | I55: =I16*'Drivers'!I$57 | J55: =J16*'Drivers'!J$57 | K55: =K16*'Drivers'!K$57 | L55: =L16*'Drivers'!L$57 | M55: =M16*'Drivers'!M$57 | N55: =N16*'Drivers'!N$57 | O55: =O16*'Drivers'!O$57 | P55: =P16*'Drivers'!P$57 | ... R55: =R16*'Drivers'!R$57
B56: Plus: stock-based compensation | C56: $mm | F56: 339 | G56: 273 | H56: 368 | I56: =I16*'Drivers'!I$58 | J56: =J16*'Drivers'!J$58 | K56: =K16*'Drivers'!K$58 | L56: =L16*'Drivers'!L$58 | M56: =M16*'Drivers'!M$58 | N56: =N16*'Drivers'!N$58 | O56: =O16*'Drivers'!O$58 | P56: =P16*'Drivers'!P$58 | ... R56: =R16*'Drivers'!R$58
B57: Less: capital expenditures | C57: $mm | F57: -349 | G57: -440 | H57: -688 | I57: =-I16*'Drivers'!I$59 | J57: =-J16*'Drivers'!J$59 | K57: =-K16*'Drivers'!K$59 | L57: =-L16*'Drivers'!L$59 | M57: =-M16*'Drivers'!M$59 | N57: =-N16*'Drivers'!N$59 | O57: =-O16*'Drivers'!O$59 | P57: =-P16*'Drivers'!P$59 | ... R57: =-R16*'Drivers'!R$59
B58: Other operating cash items | C58: $mm | F58: =7274-5408-14197+12555-357-339 | G58: =7361-8712-15302+16224-329-273 | H58: =10149-10981-16422+17097-333-368 | I58: =I16*'Drivers'!I$60 | J58: =J16*'Drivers'!J$60 | K58: =K16*'Drivers'!K$60 | L58: =L16*'Drivers'!L$60 | M58: =M16*'Drivers'!M$60 | N58: =N16*'Drivers'!N$60 | O58: =O16*'Drivers'!O$60 | P58: =P16*'Drivers'!P$60 | ... R58: =R16*'Drivers'!R$60
B59: Unlevered free cash flow | C59: $mm | I59: =I51+I52+I53+I55+I56+I57+I58 | J59: =J51+J52+J53+J55+J56+J57+J58 | K59: =K51+K52+K53+K55+K56+K57+K58 | L59: =L51+L52+L53+L55+L56+L57+L58 | M59: =M51+M52+M53+M55+M56+M57+M58 | N59: =N51+N52+N53+N55+N56+N57+N58 | O59: =O51+O52+O53+O55+O56+O57+O58 | P59: =P51+P52+P53+P55+P56+P57+P58 | ... R59: =R51+R52+R53+R55+R56+R57+R58
B60: Plus: interest and other income, after tax | C60: $mm | I60: =(I36+I37)*(1-I41) | J60: =(J36+J37)*(1-J41) | K60: =(K36+K37)*(1-K41) | L60: =(L36+L37)*(1-L41) | M60: =(M36+M37)*(1-M41) | N60: =(N36+N37)*(1-N41) | O60: =(O36+O37)*(1-O41) | P60: =(P36+P37)*(1-P41) | ... R60: =(R36+R37)*(1-R41)
B61: Free cash flow | C61: $mm | F61: =7274-349 | G61: =7361-440 | H61: =10149-688 | I61: =I59+I60 | J61: =J59+J60 | K61: =K59+K60 | L61: =L59+L60 | M61: =M59+M60 | N61: =N59+N60 | O61: =O59+O60 | P61: =P59+P60 | ... R61: =R59+R60
B62: FCF margin | C62: % | F62: =F61/F16 | G62: =G61/G16 | H62: =H61/H16 | I62: =I61/I16 | J62: =J61/J16 | K62: =K61/K16 | L62: =L61/L16 | M62: =M61/M16 | ... R62: =R61/R16
B63: FCF ex one-offs | C63: $mm | F63: =F61 | G63: =G61 | H63: =H61 | I63: =I61-I38*(1-I41) | J63: =J61-J38*(1-J41) | K63: =K61-K38*(1-K41) | L63: =L61-L38*(1-L41) | M63: =M61-M38*(1-M41) | N63: =N61-N38*(1-N41) | O63: =O61-O38*(1-O41) | P63: =P61-P38*(1-P41) | ... R63: =R61-R38*(1-R41)
B64: Cash, beginning of year | C64: $mm | I64: =H70 | J64: =I70 | K64: =J70 | L64: =K70 | M64: =L70 | N64: =M70 | O64: =N70 | P64: =O70 | ... R64: =Q70
B65: Cash held (months of revenue) | C65: $mm | I65: =I16*'Drivers'!$D$32/12 | J65: =J16*'Drivers'!$D$32/12 | K65: =K16*'Drivers'!$D$32/12 | L65: =L16*'Drivers'!$D$32/12 | M65: =M16*'Drivers'!$D$32/12 | N65: =N16*'Drivers'!$D$32/12 | O65: =O16*'Drivers'!$D$32/12 | P65: =P16*'Drivers'!$D$32/12 | ... R65: =R16*'Drivers'!$D$32/12
B66: Gross debt, end of year | C66: $mm | F66: 14543 | G66: 15583 | H66: 14463 | I66: ='Drivers'!I$65 | J66: ='Drivers'!J$65 | K66: ='Drivers'!K$65 | L66: ='Drivers'!L$65 | M66: ='Drivers'!M$65 | N66: ='Drivers'!N$65 | O66: ='Drivers'!O$65 | P66: ='Drivers'!P$65 | ... R66: ='Drivers'!R$65
B67: Debt issued / (repaid) | C67: $mm | I67: =I66-H66 | J67: =J66-I66 | K67: =K66-J66 | L67: =L66-K66 | M67: =M66-L66 | N67: =N66-M66 | O67: =O66-N66 | P67: =P66-O66 | ... R67: =R66-Q66
B68: Share repurchases (cash above the holding level) | C68: $mm | F68: -6045 | G68: -6264 | H68: -9127 | I68: =-MAX(0,I64+I61+I67-I65) | J68: =-MAX(0,J64+J61+J67-J65) | K68: =-MAX(0,K64+K61+K67-K65) | L68: =-MAX(0,L64+L61+L67-L65) | M68: =-MAX(0,M64+M61+M67-M65) | N68: =-MAX(0,N64+N61+N67-N65) | O68: =-MAX(0,O64+O61+O67-O65) | P68: =-MAX(0,P64+P61+P67-P65) | ... R68: =-MAX(0,R64+R61+R67-R65)
B69: repurchase price | C69: $ | I69: ='Drivers'!$D$34 | J69: ='Drivers'!$D$7*(1+'Drivers'!$D$35)^(J$6-$I$6) | K69: ='Drivers'!$D$7*(1+'Drivers'!$D$35)^(K$6-$I$6) | L69: ='Drivers'!$D$7*(1+'Drivers'!$D$35)^(L$6-$I$6) | M69: ='Drivers'!$D$7*(1+'Drivers'!$D$35)^(M$6-$I$6) | N69: ='Drivers'!$D$7*(1+'Drivers'!$D$35)^(N$6-$I$6) | O69: ='Drivers'!$D$7*(1+'Drivers'!$D$35)^(O$6-$I$6) | P69: ='Drivers'!$D$7*(1+'Drivers'!$D$35)^(P$6-$I$6) | Q69: ='Drivers'!$D$7*(1+'Drivers'!$D$35)^(Q$6-$I$6) | R69: ='Drivers'!$D$7*(1+'Drivers'!$D$35)^(R$6-$I$6)
B70: Cash, end of year | C70: $mm | F70: 7139 | G70: 9586 | H70: 9068 | I70: =I64+I61+I67+I68 | J70: =J64+J61+J67+J68 | K70: =K64+K61+K67+K68 | L70: =L64+L61+L67+L68 | M70: =M64+M61+M67+M68 | N70: =N64+N61+N67+N68 | O70: =O64+O61+O67+O68 | P70: =P64+P61+P67+P68 | ... R70: =R64+R61+R67+R68
B71: Net debt, end of year | C71: $mm | F71: =F66-F70 | G71: =G66-G70 | H71: =H66-H70 | I71: =I66-I70 | J71: =J66-J70 | K71: =K66-K70 | L71: =L66-L70 | M71: =M66-M70 | ... R71: =R66-R70
B72: Net debt / EBITDA | C72: x | F72: =F71/(F33+F55) | G72: =G71/(G33+G55) | H72: =H71/(H33+H55) | I72: =I71/(I33+I55) | J72: =J71/(J33+J55) | K72: =K71/(K33+K55) | L72: =L71/(L33+L55) | M72: =M71/(M33+M55) | ... R72: =R71/(R33+R55)
B73: Diluted shares, end of year | C73: mm | F73: 4428 | G73: 4358 | H73: 4300 | I73: =H73*(1+'Drivers'!$D$33)+I68/I69 | J73: =I73*(1+'Drivers'!$D$33)+J68/J69 | K73: =J73*(1+'Drivers'!$D$33)+K68/K69 | L73: =K73*(1+'Drivers'!$D$33)+L68/L69 | M73: =L73*(1+'Drivers'!$D$33)+M68/M69 | N73: =M73*(1+'Drivers'!$D$33)+N68/N69 | O73: =N73*(1+'Drivers'!$D$33)+O68/O69 | P73: =O73*(1+'Drivers'!$D$33)+P68/P69 | ... R73: =Q73*(1+'Drivers'!$D$33)+R68/R69
B74: net share reduction | C74: % | G74: =1-G73/F73 | H74: =1-H73/G73 | I74: =1-I73/H73 | J74: =1-J73/I73 | K74: =1-K73/J73 | L74: =1-L73/K73 | M74: =1-M73/L73 | N74: =1-N73/M73 | ... R74: =1-R73/Q73
B75: Content obligations, year end (memo) | C75: $mm | F75: 21700 | G75: 23200 | H75: 24039
B77: REPORTED MEMO AND TIES
B78: Operating income, reported | C78: $mm | F78: 6954 | G78: 10418 | H78: 13327
B79: Net income, reported | C79: $mm | F79: 5408 | G79: 8712 | H79: 10981
B80: Diluted EPS, reported | C80: $ | F80: 1.2 | G80: 1.98 | H80: 2.53
B81: Cash from operations, reported | C81: $mm | F81: 7274 | G81: 7361 | H81: 10149
B82: Sales and marketing | C82: $mm | F82: 2658 | G82: 2918 | H82: 3301
B83: Technology and development | C83: $mm | F83: 2676 | G83: 2925 | H83: 3391
B84: General and administrative | C84: $mm | F84: 1720 | G84: 1702 | H84: 1888
B85: Employees at year end (approx.) | C85: # | F85: 13000 | G85: 14000 | H85: 16000
B86: Tie: model less reported (operating income, net income, EPS) | C86: $mm | F86: =ABS(F33-F78)+ABS(F42-F79)+ABS(F45-F80)*100 | G86: =ABS(G33-G78)+ABS(G42-G79)+ABS(G45-G80)*100 | H86: =ABS(H33-H78)+ABS(H42-H79)+ABS(H45-H80)*100

Sheet Valuation
B1: Netflix, Inc. | Valuation
B2: ="Active scenario: "&CHOOSE('Drivers'!$D$6,"Bear","Base","Bull")&". Cash flows after the 9/30/2026 balance sheet, discounted to the valuation date at mid-period. Price path at two horizons; no dividend."
B3: Blue = input Black = formula Green = cross-sheet link $ in millions except per share; shares in millions (post-split)
B5: DISCOUNTED CASH FLOW | ACTIVE SCENARIO
B6: Fiscal year (calendar) | F6: 2023 | G6: 2024 | H6: 2025 | I6: 2026 | J6: 2027 | K6: 2028 | L6: 2029 | M6: 2030 | N6: 2031 | O6: 2032 | P6: 2033 | Q6: 2034 | R6: 2035
B7: Unlevered free cash flow | C7: $mm | I7: ='Model'!I59 | J7: ='Model'!J59 | K7: ='Model'!K59 | L7: ='Model'!L59 | M7: ='Model'!M59 | N7: ='Model'!N59 | O7: ='Model'!O59 | P7: ='Model'!P59 | ... R7: ='Model'!R59
B8: Share of the year after the balance-sheet date | C8: x | I8: =('Drivers'!$D$10-'Drivers'!$D$9)/365 | J8: =1 | K8: =1 | L8: =1 | M8: =1 | N8: =1 | O8: =1 | P8: =1 | Q8: =1 | R8: =1
B9: Cash flow counted | C9: $mm | I9: =I7*I8 | J9: =J7*J8 | K9: =K7*K8 | L9: =L7*L8 | M9: =M7*M8 | N9: =N7*N8 | O9: =O7*O8 | P9: =P7*P8 | ... R9: =R7*R8
B10: Discount period, mid-period | C10: yrs | I10: =(('Drivers'!$D$10-'Drivers'!$D$9)/2+('Drivers'!$D$9-'Drivers'!$D$8))/365 | J10: =('Drivers'!$D$10-'Drivers'!$D$8)/365+0.5 | K10: =J10+1 | L10: =K10+1 | M10: =L10+1 | N10: =M10+1 | O10: =N10+1 | P10: =O10+1 | Q10: =P10+1 | R10: =Q10+1
B11: Discount factor | C11: x | I11: =1/(1+'Drivers'!$D$29)^I10 | J11: =1/(1+'Drivers'!$D$29)^J10 | K11: =1/(1+'Drivers'!$D$29)^K10 | L11: =1/(1+'Drivers'!$D$29)^L10 | M11: =1/(1+'Drivers'!$D$29)^M10 | N11: =1/(1+'Drivers'!$D$29)^N10 | O11: =1/(1+'Drivers'!$D$29)^O10 | P11: =1/(1+'Drivers'!$D$29)^P10 | ... R11: =1/(1+'Drivers'!$D$29)^R10
B12: Present value | C12: $mm | I12: =I9*I11 | J12: =J9*J11 | K12: =K9*K11 | L12: =L9*L11 | M12: =M9*M11 | N12: =N9*N11 | O12: =O9*O11 | P12: =P9*P11 | ... R12: =R9*R11
B14: PV of forecast cash flows | C14: $mm | D14: =SUM(I12:R12)
B15: Terminal growth | C15: % | D15: ='Drivers'!$D$44
B16: Terminal value at FY2035 | C16: $mm | D16: =R7*(1+D15)/('Drivers'!$D$29-D15)
B17: PV of terminal value | C17: $mm | D17: =D16*R11
B18: Enterprise value | C18: $mm | D18: =D14+D17
B19: Less: net debt at 9/30/2026 | C19: $mm | D19: =-'Drivers'!$D$16
B20: Equity value | C20: $mm | D20: =D18+D19
B21: Diluted shares | C21: mm | D21: ='Drivers'!$D$13
B22: DCF value per share | C22: $ | D22: =D20/D21
B23: Upside / (downside) to price | C23: % | D23: =D22/'Drivers'!$D$7-1
B24: Terminal value, % of enterprise value | C24: % | D24: =D17/D18
B25: Implied terminal EV / EBITDA | C25: x | D25: =D16/('Model'!R33+'Model'!R55)
B26: P/E at DCF value on FY27E EPS | C26: x | D26: =D22/'Model'!J47
B27: EV / EBIT today on FY26E | C27: x | D27: ='Drivers'!$D$19/'Model'!I33
B29: PRICE PATH | ACTIVE SCENARIO
B30: Exit P/E (NTM) | C30: x | D30: ='Drivers'!$D$45
B31: Years to exit 1 (end of 2028) | C31: yrs | D31: =('Drivers'!$D$11-'Drivers'!$D$8)/365
B32: FY29E EPS | C32: $ | D32: ='Model'!L47
B33: Price at the end of 2028 | C33: $ | D33: =D30*D32
B34: Price at exit / price today | C34: x | D34: =D33/'Drivers'!$D$7
B35: IRR to the end of 2028 | C35: % | D35: =D34^(1/D31)-1
B36: Entry price for the hurdle IRR to exit 1 | C36: $ | D36: =D33/(1+'Drivers'!$D$36)^D31
B37: Years to exit 2 (end of 2029) | C37: yrs | D37: =('Drivers'!$D$12-'Drivers'!$D$8)/365
B38: FY30E EPS | C38: $ | D38: ='Model'!M47
B39: Price at the end of 2029 | C39: $ | D39: =D30*D38
B40: IRR to the end of 2029 | C40: % | D40: =(D39/'Drivers'!$D$7)^(1/D37)-1
B42: DCF VALUE PER SHARE: TERMINAL GROWTH (DOWN) X WACC (ACROSS)
E43: =D22 | F43: ='Drivers'!$D$29+(0-2)*'Drivers'!$D$37 | G43: ='Drivers'!$D$29+(1-2)*'Drivers'!$D$37 | H43: ='Drivers'!$D$29+(2-2)*'Drivers'!$D$37 | I43: ='Drivers'!$D$29+(3-2)*'Drivers'!$D$37 | J43: ='Drivers'!$D$29+(4-2)*'Drivers'!$D$37
E44: =$D$15+(0-2)*'Drivers'!$D$38 | F44: =(SUMPRODUCT($I$9:$R$9,(1+F$43)^(-$I$10:$R$10))+$R$7*(1+$E44)/(F$43-$E44)*(1+F$43)^(-$R$10)+$D$19)/$D$21 | G44: =(SUMPRODUCT($I$9:$R$9,(1+G$43)^(-$I$10:$R$10))+$R$7*(1+$E44)/(G$43-$E44)*(1+G$43)^(-$R$10)+$D$19)/$D$21 | H44: =(SUMPRODUCT($I$9:$R$9,(1+H$43)^(-$I$10:$R$10))+$R$7*(1+$E44)/(H$43-$E44)*(1+H$43)^(-$R$10)+$D$19)/$D$21 | I44: =(SUMPRODUCT($I$9:$R$9,(1+I$43)^(-$I$10:$R$10))+$R$7*(1+$E44)/(I$43-$E44)*(1+I$43)^(-$R$10)+$D$19)/$D$21 | J44: =(SUMPRODUCT($I$9:$R$9,(1+J$43)^(-$I$10:$R$10))+$R$7*(1+$E44)/(J$43-$E44)*(1+J$43)^(-$R$10)+$D$19)/$D$21
E45: =$D$15+(1-2)*'Drivers'!$D$38 | F45: =(SUMPRODUCT($I$9:$R$9,(1+F$43)^(-$I$10:$R$10))+$R$7*(1+$E45)/(F$43-$E45)*(1+F$43)^(-$R$10)+$D$19)/$D$21 | G45: =(SUMPRODUCT($I$9:$R$9,(1+G$43)^(-$I$10:$R$10))+$R$7*(1+$E45)/(G$43-$E45)*(1+G$43)^(-$R$10)+$D$19)/$D$21 | H45: =(SUMPRODUCT($I$9:$R$9,(1+H$43)^(-$I$10:$R$10))+$R$7*(1+$E45)/(H$43-$E45)*(1+H$43)^(-$R$10)+$D$19)/$D$21 | I45: =(SUMPRODUCT($I$9:$R$9,(1+I$43)^(-$I$10:$R$10))+$R$7*(1+$E45)/(I$43-$E45)*(1+I$43)^(-$R$10)+$D$19)/$D$21 | J45: =(SUMPRODUCT($I$9:$R$9,(1+J$43)^(-$I$10:$R$10))+$R$7*(1+$E45)/(J$43-$E45)*(1+J$43)^(-$R$10)+$D$19)/$D$21
E46: =$D$15+(2-2)*'Drivers'!$D$38 | F46: =(SUMPRODUCT($I$9:$R$9,(1+F$43)^(-$I$10:$R$10))+$R$7*(1+$E46)/(F$43-$E46)*(1+F$43)^(-$R$10)+$D$19)/$D$21 | G46: =(SUMPRODUCT($I$9:$R$9,(1+G$43)^(-$I$10:$R$10))+$R$7*(1+$E46)/(G$43-$E46)*(1+G$43)^(-$R$10)+$D$19)/$D$21 | H46: =(SUMPRODUCT($I$9:$R$9,(1+H$43)^(-$I$10:$R$10))+$R$7*(1+$E46)/(H$43-$E46)*(1+H$43)^(-$R$10)+$D$19)/$D$21 | I46: =(SUMPRODUCT($I$9:$R$9,(1+I$43)^(-$I$10:$R$10))+$R$7*(1+$E46)/(I$43-$E46)*(1+I$43)^(-$R$10)+$D$19)/$D$21 | J46: =(SUMPRODUCT($I$9:$R$9,(1+J$43)^(-$I$10:$R$10))+$R$7*(1+$E46)/(J$43-$E46)*(1+J$43)^(-$R$10)+$D$19)/$D$21
E47: =$D$15+(3-2)*'Drivers'!$D$38 | F47: =(SUMPRODUCT($I$9:$R$9,(1+F$43)^(-$I$10:$R$10))+$R$7*(1+$E47)/(F$43-$E47)*(1+F$43)^(-$R$10)+$D$19)/$D$21 | G47: =(SUMPRODUCT($I$9:$R$9,(1+G$43)^(-$I$10:$R$10))+$R$7*(1+$E47)/(G$43-$E47)*(1+G$43)^(-$R$10)+$D$19)/$D$21 | H47: =(SUMPRODUCT($I$9:$R$9,(1+H$43)^(-$I$10:$R$10))+$R$7*(1+$E47)/(H$43-$E47)*(1+H$43)^(-$R$10)+$D$19)/$D$21 | I47: =(SUMPRODUCT($I$9:$R$9,(1+I$43)^(-$I$10:$R$10))+$R$7*(1+$E47)/(I$43-$E47)*(1+I$43)^(-$R$10)+$D$19)/$D$21 | J47: =(SUMPRODUCT($I$9:$R$9,(1+J$43)^(-$I$10:$R$10))+$R$7*(1+$E47)/(J$43-$E47)*(1+J$43)^(-$R$10)+$D$19)/$D$21
E48: =$D$15+(4-2)*'Drivers'!$D$38 | F48: =(SUMPRODUCT($I$9:$R$9,(1+F$43)^(-$I$10:$R$10))+$R$7*(1+$E48)/(F$43-$E48)*(1+F$43)^(-$R$10)+$D$19)/$D$21 | G48: =(SUMPRODUCT($I$9:$R$9,(1+G$43)^(-$I$10:$R$10))+$R$7*(1+$E48)/(G$43-$E48)*(1+G$43)^(-$R$10)+$D$19)/$D$21 | H48: =(SUMPRODUCT($I$9:$R$9,(1+H$43)^(-$I$10:$R$10))+$R$7*(1+$E48)/(H$43-$E48)*(1+H$43)^(-$R$10)+$D$19)/$D$21 | I48: =(SUMPRODUCT($I$9:$R$9,(1+I$43)^(-$I$10:$R$10))+$R$7*(1+$E48)/(I$43-$E48)*(1+I$43)^(-$R$10)+$D$19)/$D$21 | J48: =(SUMPRODUCT($I$9:$R$9,(1+J$43)^(-$I$10:$R$10))+$R$7*(1+$E48)/(J$43-$E48)*(1+J$43)^(-$R$10)+$D$19)/$D$21
B50: PRICE PATH: EXIT P/E (ACROSS) AT EACH HORIZON
B51: Exit P/E (NTM) | C51: x | F51: =$D$30+(0-3)*'Drivers'!$D$39 | G51: =$D$30+(1-3)*'Drivers'!$D$39 | H51: =$D$30+(2-3)*'Drivers'!$D$39 | I51: =$D$30+(3-3)*'Drivers'!$D$39 | J51: =$D$30+(4-3)*'Drivers'!$D$39 | K51: =$D$30+(5-3)*'Drivers'!$D$39 | L51: =$D$30+(6-3)*'Drivers'!$D$39
B52: Price at the end of 2028 | C52: $ | F52: =F51*$D$32 | G52: =G51*$D$32 | H52: =H51*$D$32 | I52: =I51*$D$32 | J52: =J51*$D$32 | K52: =K51*$D$32 | L52: =L51*$D$32
B53: IRR to the end of 2028 | C53: % | F53: =(F52/'Drivers'!$D$7)^(1/$D$31)-1 | G53: =(G52/'Drivers'!$D$7)^(1/$D$31)-1 | H53: =(H52/'Drivers'!$D$7)^(1/$D$31)-1 | I53: =(I52/'Drivers'!$D$7)^(1/$D$31)-1 | J53: =(J52/'Drivers'!$D$7)^(1/$D$31)-1 | K53: =(K52/'Drivers'!$D$7)^(1/$D$31)-1 | L53: =(L52/'Drivers'!$D$7)^(1/$D$31)-1
B54: Price at the end of 2029 | C54: $ | F54: =F51*$D$38 | G54: =G51*$D$38 | H54: =H51*$D$38 | I54: =I51*$D$38 | J54: =J51*$D$38 | K54: =K51*$D$38 | L54: =L51*$D$38
B55: IRR to the end of 2029 | C55: % | F55: =(F54/'Drivers'!$D$7)^(1/$D$37)-1 | G55: =(G54/'Drivers'!$D$7)^(1/$D$37)-1 | H55: =(H54/'Drivers'!$D$7)^(1/$D$37)-1 | I55: =(I54/'Drivers'!$D$7)^(1/$D$37)-1 | J55: =(J54/'Drivers'!$D$7)^(1/$D$37)-1 | K55: =(K54/'Drivers'!$D$7)^(1/$D$37)-1 | L55: =(L54/'Drivers'!$D$7)^(1/$D$37)-1
B56: Entry price for the hurdle IRR (exit 1) | C56: $ | F56: =F52/(1+'Drivers'!$D$36)^$D$31 | G56: =G52/(1+'Drivers'!$D$36)^$D$31 | H56: =H52/(1+'Drivers'!$D$36)^$D$31 | I56: =I52/(1+'Drivers'!$D$36)^$D$31 | J56: =J52/(1+'Drivers'!$D$36)^$D$31 | K56: =K52/(1+'Drivers'!$D$36)^$D$31 | L56: =L52/(1+'Drivers'!$D$36)^$D$31

Sheet Scenarios
B1: Netflix, Inc. | Scenarios
B2: Three complete chains, always live, independent of the Drivers switch. The comparison table feeds the Summary.
B3: Blue = input Black = formula Green = cross-sheet link $ in millions except per share; shares in millions (post-split)
B5: COMPARISON
F6: Bear | G6: Base | H6: Bull | I6: Weighted
B7: Probability | C7: % | F7: ='Drivers'!$F$43 | G7: ='Drivers'!$G$43 | H7: ='Drivers'!$H$43 | I7: =SUM(F7:H7)
B8: FY26E revenue growth | C8: % | F8: =I50 | G8: =I162 | H8: =I274
B9: FY27E revenue growth | C9: % | F9: =J50 | G9: =J162 | H9: =J274
B10: FY28E advertising revenue | C10: $mm | F10: =K51 | G10: =K163 | H10: =K275
B11: FY27E operating margin | C11: % | F11: =J67 | G11: =J179 | H11: =J291
B12: FY29E operating margin | C12: % | F12: =L67 | G12: =L179 | H12: =L291
B13: FY26E EPS, GAAP (with the fee) | C13: $ | F13: =I78 | G13: =I190 | H13: =I302 | I13: =SUMPRODUCT($F$7:$H$7,F13:H13)
B14: FY26E EPS ex the fee | C14: $ | F14: =I80 | G14: =I192 | H14: =I304 | I14: =SUMPRODUCT($F$7:$H$7,F14:H14)
B15: FY27E EPS | C15: $ | F15: =J80 | G15: =J192 | H15: =J304 | I15: =SUMPRODUCT($F$7:$H$7,F15:H15)
B16: FY29E EPS | C16: $ | F16: =L80 | G16: =L192 | H16: =L304 | I16: =SUMPRODUCT($F$7:$H$7,F16:H16)
B17: FY30E EPS | C17: $ | F17: =M80 | G17: =M192 | H17: =M304 | I17: =SUMPRODUCT($F$7:$H$7,F17:H17)
B18: FY29E revenue | C18: $mm | F18: =L49 | G18: =L161 | H18: =L273
B19: FY27E free cash flow | C19: $mm | F19: =J94 | G19: =J206 | H19: =J318
B20: FY27E share repurchases | C20: $mm | F20: =-J101 | G20: =-J213 | H20: =-J325
B21: FY29E diluted shares | C21: mm | F21: =L77 | G21: =L189 | H21: =L301
B22: Terminal growth | C22: % | F22: ='Drivers'!$F$44 | G22: ='Drivers'!$G$44 | H22: ='Drivers'!$H$44
B23: Implied terminal EV / EBITDA | C23: x | F23: =D130 | G23: =D242 | H23: =D354
B24: DCF value per share | C24: $ | F24: =D127 | G24: =D239 | H24: =D351 | I24: =SUMPRODUCT($F$7:$H$7,F24:H24)
B25: vs price | C25: % | F25: =F24/'Drivers'!$D$7-1 | G25: =G24/'Drivers'!$D$7-1 | H25: =H24/'Drivers'!$D$7-1 | I25: =I24/'Drivers'!$D$7-1
B26: Exit P/E (NTM) | C26: x | F26: =D135 | G26: =D247 | H26: =D359
B27: Price at the end of 2028 | C27: $ | F27: =D138 | G27: =D250 | H27: =D362 | I27: =SUMPRODUCT($F$7:$H$7,F27:H27)
B28: IRR to the end of 2028 | C28: % | F28: =D140 | G28: =D252 | H28: =D364 | I28: =(I27/'Drivers'!$D$7)^(1/D136)-1
B29: Price at the end of 2029 | C29: $ | F29: =D144 | G29: =D256 | H29: =D368 | I29: =SUMPRODUCT($F$7:$H$7,F29:H29)
B30: IRR to the end of 2029 | C30: % | F30: =D145 | G30: =D257 | H30: =D369 | I30: =(I29/'Drivers'!$D$7)^(1/D142)-1
B31: Entry price for the hurdle IRR (exit 1) | C31: $ | F31: =D141 | G31: =D253 | H31: =D365 | I31: =SUMPRODUCT($F$7:$H$7,F31:H31)
B36: BEAR CASE
B38: REVENUE | BEAR CASE
B39: Fiscal year (calendar) | F39: 2023 | G39: 2024 | H39: 2025 | I39: 2026 | J39: 2027 | K39: 2028 | L39: 2029 | M39: 2030 | N39: 2031 | O39: 2032 | P39: 2033 | Q39: 2034 | R39: 2035
B40: United States and Canada | C40: $mm | F40: ='Model'!F7 | G40: ='Model'!G7 | H40: ='Model'!H7 | I40: =H40*(1+I41) | J40: =I40*(1+J41) | K40: =J40*(1+K41) | L40: =K40*(1+L41) | M40: =L40*(1+M41) | N40: =M40*(1+N41) | O40: =N40*(1+O41) | P40: =O40*(1+P41) | ... R40: =Q40*(1+R41)
B41: y/y | C41: % | G41: ='Model'!G8 | H41: ='Model'!H8 | I41: ='Drivers'!I$69 | J41: ='Drivers'!J$69 | K41: ='Drivers'!K$69 | L41: ='Drivers'!L$69 | M41: ='Drivers'!M$69 | N41: ='Drivers'!N$69 | O41: ='Drivers'!O$69 | P41: ='Drivers'!P$69 | ... R41: ='Drivers'!R$69
B42: Europe, Middle East and Africa | C42: $mm | F42: ='Model'!F9 | G42: ='Model'!G9 | H42: ='Model'!H9 | I42: =H42*(1+I43) | J42: =I42*(1+J43) | K42: =J42*(1+K43) | L42: =K42*(1+L43) | M42: =L42*(1+M43) | N42: =M42*(1+N43) | O42: =N42*(1+O43) | P42: =O42*(1+P43) | ... R42: =Q42*(1+R43)
B43: y/y | C43: % | G43: ='Model'!G10 | H43: ='Model'!H10 | I43: ='Drivers'!I$72 | J43: ='Drivers'!J$72 | K43: ='Drivers'!K$72 | L43: ='Drivers'!L$72 | M43: ='Drivers'!M$72 | N43: ='Drivers'!N$72 | O43: ='Drivers'!O$72 | P43: ='Drivers'!P$72 | ... R43: ='Drivers'!R$72
B44: Latin America | C44: $mm | F44: ='Model'!F11 | G44: ='Model'!G11 | H44: ='Model'!H11 | I44: =H44*(1+I45) | J44: =I44*(1+J45) | K44: =J44*(1+K45) | L44: =K44*(1+L45) | M44: =L44*(1+M45) | N44: =M44*(1+N45) | O44: =N44*(1+O45) | P44: =O44*(1+P45) | ... R44: =Q44*(1+R45)
B45: y/y | C45: % | G45: ='Model'!G12 | H45: ='Model'!H12 | I45: ='Drivers'!I$75 | J45: ='Drivers'!J$75 | K45: ='Drivers'!K$75 | L45: ='Drivers'!L$75 | M45: ='Drivers'!M$75 | N45: ='Drivers'!N$75 | O45: ='Drivers'!O$75 | P45: ='Drivers'!P$75 | ... R45: ='Drivers'!R$75
B46: Asia-Pacific | C46: $mm | F46: ='Model'!F13 | G46: ='Model'!G13 | H46: ='Model'!H13 | I46: =H46*(1+I47) | J46: =I46*(1+J47) | K46: =J46*(1+K47) | L46: =K46*(1+L47) | M46: =L46*(1+M47) | N46: =M46*(1+N47) | O46: =N46*(1+O47) | P46: =O46*(1+P47) | ... R46: =Q46*(1+R47)
B47: y/y | C47: % | G47: ='Model'!G14 | H47: ='Model'!H14 | I47: ='Drivers'!I$78 | J47: ='Drivers'!J$78 | K47: ='Drivers'!K$78 | L47: ='Drivers'!L$78 | M47: ='Drivers'!M$78 | N47: ='Drivers'!N$78 | O47: ='Drivers'!O$78 | P47: ='Drivers'!P$78 | ... R47: ='Drivers'!R$78
B48: DVD (wound down 2023) | C48: $mm | F48: ='Model'!F15 | G48: ='Model'!G15 | H48: ='Model'!H15 | I48: =0 | J48: =0 | K48: =0 | L48: =0 | M48: =0 | N48: =0 | O48: =0 | P48: =0 | ... R48: =0
B49: Total revenue | C49: $mm | F49: ='Model'!F16 | G49: ='Model'!G16 | H49: ='Model'!H16 | I49: =I40+I42+I44+I46+I48 | J49: =J40+J42+J44+J46+J48 | K49: =K40+K42+K44+K46+K48 | L49: =L40+L42+L44+L46+L48 | M49: =M40+M42+M44+M46+M48 | N49: =N40+N42+N44+N46+N48 | O49: =O40+O42+O44+O46+O48 | P49: =P40+P42+P44+P46+P48 | ... R49: =R40+R42+R44+R46+R48
B50: y/y | C50: % | G50: ='Model'!G17 | H50: ='Model'!H17 | I50: =I49/H49-1 | J50: =J49/I49-1 | K50: =K49/J49-1 | L50: =L49/K49-1 | M50: =M49/L49-1 | N50: =N49/M49-1 | O50: =O49/N49-1 | P50: =P49/O49-1 | ... R50: =R49/Q49-1
B51: of which advertising (memo) | C51: $mm | G51: ='Model'!G18 | H51: ='Model'!H18 | I51: ='Drivers'!I$81 | J51: ='Drivers'!J$81 | K51: ='Drivers'!K$81 | L51: ='Drivers'!L$81 | M51: ='Drivers'!M$81 | N51: ='Drivers'!N$81 | O51: ='Drivers'!O$81 | P51: ='Drivers'!P$81 | ... R51: ='Drivers'!R$81
B52: advertising, % of revenue | C52: % | G52: ='Model'!G19 | H52: ='Model'!H19 | I52: =I51/I49 | J52: =J51/J49 | K52: =K51/K49 | L52: =L51/L49 | M52: =M51/M49 | N52: =N51/N49 | O52: =O51/O49 | P52: =P51/P49 | ... R52: =R51/R49
B53: subscription and other (memo) | C53: $mm | G53: ='Model'!G20 | H53: ='Model'!H20 | I53: =I49-I51 | J53: =J49-J51 | K53: =K49-K51 | L53: =L49-L51 | M53: =M49-M51 | N53: =N49-N51 | O53: =O49-O51 | P53: =P49-P51 | ... R53: =R49-R51
B54: y/y | C54: % | H54: ='Model'!H21 | I54: =I53/H53-1 | J54: =J53/I53-1 | K54: =K53/J53-1 | L54: =L53/K53-1 | M54: =M53/L53-1 | N54: =N53/M53-1 | O54: =O53/N53-1 | P54: =P53/O53-1 | ... R54: =R53/Q53-1
B56: INCOME STATEMENT
B57: Content amortization | C57: $mm | F57: ='Model'!F24 | G57: ='Model'!G24 | H57: ='Model'!H24 | I57: =H57*(1+I58) | J57: =I57*(1+J58) | K57: =J57*(1+K58) | L57: =K57*(1+L58) | M57: =L57*(1+M58) | N57: =M57*(1+N58) | O57: =N57*(1+O58) | P57: =O57*(1+P58) | ... R57: =Q57*(1+R58)
B58: y/y | C58: % | G58: ='Model'!G25 | H58: ='Model'!H25 | I58: ='Drivers'!I$84 | J58: ='Drivers'!J$84 | K58: ='Drivers'!K$84 | L58: ='Drivers'!L$84 | M58: ='Drivers'!M$84 | N58: ='Drivers'!N$84 | O58: ='Drivers'!O$84 | P58: ='Drivers'!P$84 | ... R58: ='Drivers'!R$84
B59: % of revenue | C59: % | F59: ='Model'!F26 | G59: ='Model'!G26 | H59: ='Model'!H26 | I59: =I57/I49 | J59: =J57/J49 | K59: =K57/K49 | L59: =L57/L49 | M59: =M57/M49 | N59: =N57/N49 | O59: =O57/O49 | P59: =P57/P49 | ... R59: =R57/R49
B60: Other cost of revenues | C60: $mm | F60: ='Model'!F27 | G60: ='Model'!G27 | H60: ='Model'!H27 | I60: =I49*I61 | J60: =J49*J61 | K60: =K49*K61 | L60: =L49*L61 | M60: =M49*M61 | N60: =N49*N61 | O60: =O49*O61 | P60: =P49*P61 | ... R60: =R49*R61
B61: % of revenue | C61: % | F61: ='Model'!F28 | G61: ='Model'!G28 | H61: ='Model'!H28 | I61: ='Drivers'!I$87 | J61: ='Drivers'!J$87 | K61: ='Drivers'!K$87 | L61: ='Drivers'!L$87 | M61: ='Drivers'!M$87 | N61: ='Drivers'!N$87 | O61: ='Drivers'!O$87 | P61: ='Drivers'!P$87 | ... R61: ='Drivers'!R$87
B62: Gross profit | C62: $mm | F62: ='Model'!F29 | G62: ='Model'!G29 | H62: ='Model'!H29 | I62: =I49-I57-I60 | J62: =J49-J57-J60 | K62: =K49-K57-K60 | L62: =L49-L57-L60 | M62: =M49-M57-M60 | N62: =N49-N57-N60 | O62: =O49-O57-O60 | P62: =P49-P57-P60 | ... R62: =R49-R57-R60
B63: gross margin | C63: % | F63: ='Model'!F30 | G63: ='Model'!G30 | H63: ='Model'!H30 | I63: =I62/I49 | J63: =J62/J49 | K63: =K62/K49 | L63: =L62/L49 | M63: =M62/M49 | N63: =N62/N49 | O63: =O62/O49 | P63: =P62/P49 | ... R63: =R62/R49
B64: Operating expenses (sales and marketing, technology, G&A) | C64: $mm | F64: ='Model'!F31 | G64: ='Model'!G31 | H64: ='Model'!H31 | I64: =I49*I65 | J64: =J49*J65 | K64: =K49*K65 | L64: =L49*L65 | M64: =M49*M65 | N64: =N49*N65 | O64: =O49*O65 | P64: =P49*P65 | ... R64: =R49*R65
B65: % of revenue | C65: % | F65: ='Model'!F32 | G65: ='Model'!G32 | H65: ='Model'!H32 | I65: ='Drivers'!I$90 | J65: ='Drivers'!J$90 | K65: ='Drivers'!K$90 | L65: ='Drivers'!L$90 | M65: ='Drivers'!M$90 | N65: ='Drivers'!N$90 | O65: ='Drivers'!O$90 | P65: ='Drivers'!P$90 | ... R65: ='Drivers'!R$90
B66: Operating income | C66: $mm | F66: ='Model'!F33 | G66: ='Model'!G33 | H66: ='Model'!H33 | I66: =I62-I64 | J66: =J62-J64 | K66: =K62-K64 | L66: =L62-L64 | M66: =M62-M64 | N66: =N62-N64 | O66: =O62-O64 | P66: =P62-P64 | ... R66: =R62-R64
B67: operating margin | C67: % | F67: ='Model'!F34 | G67: ='Model'!G34 | H67: ='Model'!H34 | I67: =I66/I49 | J67: =J66/J49 | K67: =K66/K49 | L67: =L66/L49 | M67: =M66/M49 | N67: =N66/N49 | O67: =O66/O49 | P67: =P66/P49 | ... R67: =R66/R49
B68: y/y | C68: % | G68: ='Model'!G35 | H68: ='Model'!H35 | I68: =I66/H66-1 | J68: =J66/I66-1 | K68: =K66/J66-1 | L68: =L66/K66-1 | M68: =M66/L66-1 | N68: =N66/M66-1 | O68: =O66/N66-1 | P68: =P66/O66-1 | ... R68: =R66/Q66-1
B69: Interest expense | C69: $mm | F69: ='Model'!F36 | G69: ='Model'!G36 | H69: ='Model'!H36 | I69: =-H99*'Drivers'!I$62 | J69: =-I99*'Drivers'!J$62 | K69: =-J99*'Drivers'!K$62 | L69: =-K99*'Drivers'!L$62 | M69: =-L99*'Drivers'!M$62 | N69: =-M99*'Drivers'!N$62 | O69: =-N99*'Drivers'!O$62 | P69: =-O99*'Drivers'!P$62 | ... R69: =-Q99*'Drivers'!R$62
B70: Interest and other income (expense) | C70: $mm | F70: ='Model'!F37 | G70: ='Model'!G37 | H70: ='Model'!H37 | I70: =I97*'Drivers'!I$63+I71 | J70: =J97*'Drivers'!J$63+J71 | K70: =K97*'Drivers'!K$63+K71 | L70: =L97*'Drivers'!L$63+L71 | M70: =M97*'Drivers'!M$63+M71 | N70: =N97*'Drivers'!N$63+N71 | O70: =O97*'Drivers'!O$63+O71 | P70: =P97*'Drivers'!P$63+P71 | ... R70: =R97*'Drivers'!R$63+R71
B71: of which one-off (WBD termination fee) | C71: $mm | F71: ='Model'!F38 | G71: ='Model'!G38 | H71: ='Model'!H38 | I71: ='Drivers'!I$64 | J71: ='Drivers'!J$64 | K71: ='Drivers'!K$64 | L71: ='Drivers'!L$64 | M71: ='Drivers'!M$64 | N71: ='Drivers'!N$64 | O71: ='Drivers'!O$64 | P71: ='Drivers'!P$64 | ... R71: ='Drivers'!R$64
B72: Income before income taxes | C72: $mm | F72: ='Model'!F39 | G72: ='Model'!G39 | H72: ='Model'!H39 | I72: =I66+I69+I70 | J72: =J66+J69+J70 | K72: =K66+K69+K70 | L72: =L66+L69+L70 | M72: =M66+M69+M70 | N72: =N66+N69+N70 | O72: =O66+O69+O70 | P72: =P66+P69+P70 | ... R72: =R66+R69+R70
B73: Provision for income taxes | C73: $mm | F73: ='Model'!F40 | G73: ='Model'!G40 | H73: ='Model'!H40 | I73: =I72*I74 | J73: =J72*J74 | K73: =K72*K74 | L73: =L72*L74 | M73: =M72*M74 | N73: =N72*N74 | O73: =O72*O74 | P73: =P72*P74 | ... R73: =R72*R74
B74: effective tax rate | C74: % | F74: ='Model'!F41 | G74: ='Model'!G41 | H74: ='Model'!H41 | I74: ='Drivers'!I$61 | J74: ='Drivers'!J$61 | K74: ='Drivers'!K$61 | L74: ='Drivers'!L$61 | M74: ='Drivers'!M$61 | N74: ='Drivers'!N$61 | O74: ='Drivers'!O$61 | P74: ='Drivers'!P$61 | ... R74: ='Drivers'!R$61
B75: Net income | C75: $mm | F75: ='Model'!F42 | G75: ='Model'!G42 | H75: ='Model'!H42 | I75: =I72-I73 | J75: =J72-J73 | K75: =K72-K73 | L75: =L72-L73 | M75: =M72-M73 | N75: =N72-N73 | O75: =O72-O73 | P75: =P72-P73 | ... R75: =R72-R73
B76: net margin | C76: % | F76: ='Model'!F43 | G76: ='Model'!G43 | H76: ='Model'!H43 | I76: =I75/I49 | J76: =J75/J49 | K76: =K75/K49 | L76: =L75/L49 | M76: =M75/M49 | N76: =N75/N49 | O76: =O75/O49 | P76: =P75/P49 | ... R76: =R75/R49
B77: Diluted shares, weighted average | C77: mm | F77: ='Model'!F44 | G77: ='Model'!G44 | H77: ='Model'!H44 | I77: =(H106+I106)/2 | J77: =(I106+J106)/2 | K77: =(J106+K106)/2 | L77: =(K106+L106)/2 | M77: =(L106+M106)/2 | N77: =(M106+N106)/2 | O77: =(N106+O106)/2 | P77: =(O106+P106)/2 | ... R77: =(Q106+R106)/2
B78: Diluted EPS, GAAP | C78: $ | F78: ='Model'!F45 | G78: ='Model'!G45 | H78: ='Model'!H45 | I78: =I75/I77 | J78: =J75/J77 | K78: =K75/K77 | L78: =L75/L77 | M78: =M75/M77 | N78: =N75/N77 | O78: =O75/O77 | P78: =P75/P77 | ... R78: =R75/R77
B79: y/y | C79: % | G79: ='Model'!G46 | H79: ='Model'!H46 | I79: =I78/H78-1 | J79: =J78/I78-1 | K79: =K78/J78-1 | L79: =L78/K78-1 | M79: =M78/L78-1 | N79: =N78/M78-1 | O79: =O78/N78-1 | P79: =P78/O78-1 | ... R79: =R78/Q78-1
B80: Diluted EPS ex one-offs | C80: $ | F80: ='Model'!F47 | G80: ='Model'!G47 | H80: ='Model'!H47 | I80: =(I72-I71)*(1-I74)/I77 | J80: =(J72-J71)*(1-J74)/J77 | K80: =(K72-K71)*(1-K74)/K77 | L80: =(L72-L71)*(1-L74)/L77 | M80: =(M72-M71)*(1-M74)/M77 | N80: =(N72-N71)*(1-N74)/N77 | O80: =(O72-O71)*(1-O74)/O77 | P80: =(P72-P71)*(1-P74)/P77 | ... R80: =(R72-R71)*(1-R74)/R77
B81: y/y | C81: % | G81: ='Model'!G48 | H81: ='Model'!H48 | I81: =I80/H80-1 | J81: =J80/I80-1 | K81: =K80/J80-1 | L81: =L80/K80-1 | M81: =M80/L80-1 | N81: =N80/M80-1 | O81: =O80/N80-1 | P81: =P80/O80-1 | ... R81: =R80/Q80-1
B83: CASH FLOW, BUYBACKS AND NET DEBT
B84: NOPAT (operating income after tax) | C84: $mm | I84: =I66*(1-I74) | J84: =J66*(1-J74) | K84: =K66*(1-K74) | L84: =L66*(1-L74) | M84: =M66*(1-M74) | N84: =N66*(1-N74) | O84: =O66*(1-O74) | P84: =P66*(1-P74) | ... R84: =R66*(1-R74)
B85: Plus: content amortization | C85: $mm | F85: ='Model'!F52 | G85: ='Model'!G52 | H85: ='Model'!H52 | I85: =I57 | J85: =J57 | K85: =K57 | L85: =L57 | M85: =M57 | N85: =N57 | O85: =O57 | P85: =P57 | ... R85: =R57
B86: Less: cash content spend | C86: $mm | F86: ='Model'!F53 | G86: ='Model'!G53 | H86: ='Model'!H53 | I86: =-I57*'Drivers'!I$56 | J86: =-J57*'Drivers'!J$56 | K86: =-K57*'Drivers'!K$56 | L86: =-L57*'Drivers'!L$56 | M86: =-M57*'Drivers'!M$56 | N86: =-N57*'Drivers'!N$56 | O86: =-O57*'Drivers'!O$56 | P86: =-P57*'Drivers'!P$56 | ... R86: =-R57*'Drivers'!R$56
B87: cash content spend / amortization | C87: x | F87: ='Model'!F54 | G87: ='Model'!G54 | H87: ='Model'!H54 | I87: =-I86/I85 | J87: =-J86/J85 | K87: =-K86/K85 | L87: =-L86/L85 | M87: =-M86/M85 | N87: =-N86/N85 | O87: =-O86/O85 | P87: =-P86/P85 | ... R87: =-R86/R85
B88: Plus: depreciation and amortization ex content | C88: $mm | F88: ='Model'!F55 | G88: ='Model'!G55 | H88: ='Model'!H55 | I88: =I49*'Drivers'!I$57 | J88: =J49*'Drivers'!J$57 | K88: =K49*'Drivers'!K$57 | L88: =L49*'Drivers'!L$57 | M88: =M49*'Drivers'!M$57 | N88: =N49*'Drivers'!N$57 | O88: =O49*'Drivers'!O$57 | P88: =P49*'Drivers'!P$57 | ... R88: =R49*'Drivers'!R$57
B89: Plus: stock-based compensation | C89: $mm | F89: ='Model'!F56 | G89: ='Model'!G56 | H89: ='Model'!H56 | I89: =I49*'Drivers'!I$58 | J89: =J49*'Drivers'!J$58 | K89: =K49*'Drivers'!K$58 | L89: =L49*'Drivers'!L$58 | M89: =M49*'Drivers'!M$58 | N89: =N49*'Drivers'!N$58 | O89: =O49*'Drivers'!O$58 | P89: =P49*'Drivers'!P$58 | ... R89: =R49*'Drivers'!R$58
B90: Less: capital expenditures | C90: $mm | F90: ='Model'!F57 | G90: ='Model'!G57 | H90: ='Model'!H57 | I90: =-I49*'Drivers'!I$59 | J90: =-J49*'Drivers'!J$59 | K90: =-K49*'Drivers'!K$59 | L90: =-L49*'Drivers'!L$59 | M90: =-M49*'Drivers'!M$59 | N90: =-N49*'Drivers'!N$59 | O90: =-O49*'Drivers'!O$59 | P90: =-P49*'Drivers'!P$59 | ... R90: =-R49*'Drivers'!R$59
B91: Other operating cash items | C91: $mm | F91: ='Model'!F58 | G91: ='Model'!G58 | H91: ='Model'!H58 | I91: =I49*'Drivers'!I$60 | J91: =J49*'Drivers'!J$60 | K91: =K49*'Drivers'!K$60 | L91: =L49*'Drivers'!L$60 | M91: =M49*'Drivers'!M$60 | N91: =N49*'Drivers'!N$60 | O91: =O49*'Drivers'!O$60 | P91: =P49*'Drivers'!P$60 | ... R91: =R49*'Drivers'!R$60
B92: Unlevered free cash flow | C92: $mm | I92: =I84+I85+I86+I88+I89+I90+I91 | J92: =J84+J85+J86+J88+J89+J90+J91 | K92: =K84+K85+K86+K88+K89+K90+K91 | L92: =L84+L85+L86+L88+L89+L90+L91 | M92: =M84+M85+M86+M88+M89+M90+M91 | N92: =N84+N85+N86+N88+N89+N90+N91 | O92: =O84+O85+O86+O88+O89+O90+O91 | P92: =P84+P85+P86+P88+P89+P90+P91 | ... R92: =R84+R85+R86+R88+R89+R90+R91
B93: Plus: interest and other income, after tax | C93: $mm | I93: =(I69+I70)*(1-I74) | J93: =(J69+J70)*(1-J74) | K93: =(K69+K70)*(1-K74) | L93: =(L69+L70)*(1-L74) | M93: =(M69+M70)*(1-M74) | N93: =(N69+N70)*(1-N74) | O93: =(O69+O70)*(1-O74) | P93: =(P69+P70)*(1-P74) | ... R93: =(R69+R70)*(1-R74)
B94: Free cash flow | C94: $mm | F94: ='Model'!F61 | G94: ='Model'!G61 | H94: ='Model'!H61 | I94: =I92+I93 | J94: =J92+J93 | K94: =K92+K93 | L94: =L92+L93 | M94: =M92+M93 | N94: =N92+N93 | O94: =O92+O93 | P94: =P92+P93 | ... R94: =R92+R93
B95: FCF margin | C95: % | F95: ='Model'!F62 | G95: ='Model'!G62 | H95: ='Model'!H62 | I95: =I94/I49 | J95: =J94/J49 | K95: =K94/K49 | L95: =L94/L49 | M95: =M94/M49 | N95: =N94/N49 | O95: =O94/O49 | P95: =P94/P49 | ... R95: =R94/R49
B96: FCF ex one-offs | C96: $mm | F96: ='Model'!F63 | G96: ='Model'!G63 | H96: ='Model'!H63 | I96: =I94-I71*(1-I74) | J96: =J94-J71*(1-J74) | K96: =K94-K71*(1-K74) | L96: =L94-L71*(1-L74) | M96: =M94-M71*(1-M74) | N96: =N94-N71*(1-N74) | O96: =O94-O71*(1-O74) | P96: =P94-P71*(1-P74) | ... R96: =R94-R71*(1-R74)
B97: Cash, beginning of year | C97: $mm | I97: =H103 | J97: =I103 | K97: =J103 | L97: =K103 | M97: =L103 | N97: =M103 | O97: =N103 | P97: =O103 | ... R97: =Q103
B98: Cash held (months of revenue) | C98: $mm | I98: =I49*'Drivers'!$D$32/12 | J98: =J49*'Drivers'!$D$32/12 | K98: =K49*'Drivers'!$D$32/12 | L98: =L49*'Drivers'!$D$32/12 | M98: =M49*'Drivers'!$D$32/12 | N98: =N49*'Drivers'!$D$32/12 | O98: =O49*'Drivers'!$D$32/12 | P98: =P49*'Drivers'!$D$32/12 | ... R98: =R49*'Drivers'!$D$32/12
B99: Gross debt, end of year | C99: $mm | F99: ='Model'!F66 | G99: ='Model'!G66 | H99: ='Model'!H66 | I99: ='Drivers'!I$65 | J99: ='Drivers'!J$65 | K99: ='Drivers'!K$65 | L99: ='Drivers'!L$65 | M99: ='Drivers'!M$65 | N99: ='Drivers'!N$65 | O99: ='Drivers'!O$65 | P99: ='Drivers'!P$65 | ... R99: ='Drivers'!R$65
B100: Debt issued / (repaid) | C100: $mm | I100: =I99-H99 | J100: =J99-I99 | K100: =K99-J99 | L100: =L99-K99 | M100: =M99-L99 | N100: =N99-M99 | O100: =O99-N99 | P100: =P99-O99 | ... R100: =R99-Q99
B101: Share repurchases (cash above the holding level) | C101: $mm | F101: ='Model'!F68 | G101: ='Model'!G68 | H101: ='Model'!H68 | I101: =-MAX(0,I97+I94+I100-I98) | J101: =-MAX(0,J97+J94+J100-J98) | K101: =-MAX(0,K97+K94+K100-K98) | L101: =-MAX(0,L97+L94+L100-L98) | M101: =-MAX(0,M97+M94+M100-M98) | N101: =-MAX(0,N97+N94+N100-N98) | O101: =-MAX(0,O97+O94+O100-O98) | P101: =-MAX(0,P97+P94+P100-P98) | ... R101: =-MAX(0,R97+R94+R100-R98)
B102: repurchase price | C102: $ | I102: ='Drivers'!$D$34 | J102: ='Drivers'!$D$7*(1+'Drivers'!$D$35)^(J$39-$I$39) | K102: ='Drivers'!$D$7*(1+'Drivers'!$D$35)^(K$39-$I$39) | L102: ='Drivers'!$D$7*(1+'Drivers'!$D$35)^(L$39-$I$39) | M102: ='Drivers'!$D$7*(1+'Drivers'!$D$35)^(M$39-$I$39) | N102: ='Drivers'!$D$7*(1+'Drivers'!$D$35)^(N$39-$I$39) | O102: ='Drivers'!$D$7*(1+'Drivers'!$D$35)^(O$39-$I$39) | P102: ='Drivers'!$D$7*(1+'Drivers'!$D$35)^(P$39-$I$39) | Q102: ='Drivers'!$D$7*(1+'Drivers'!$D$35)^(Q$39-$I$39) | R102: ='Drivers'!$D$7*(1+'Drivers'!$D$35)^(R$39-$I$39)
B103: Cash, end of year | C103: $mm | F103: ='Model'!F70 | G103: ='Model'!G70 | H103: ='Model'!H70 | I103: =I97+I94+I100+I101 | J103: =J97+J94+J100+J101 | K103: =K97+K94+K100+K101 | L103: =L97+L94+L100+L101 | M103: =M97+M94+M100+M101 | N103: =N97+N94+N100+N101 | O103: =O97+O94+O100+O101 | P103: =P97+P94+P100+P101 | ... R103: =R97+R94+R100+R101
B104: Net debt, end of year | C104: $mm | F104: ='Model'!F71 | G104: ='Model'!G71 | H104: ='Model'!H71 | I104: =I99-I103 | J104: =J99-J103 | K104: =K99-K103 | L104: =L99-L103 | M104: =M99-M103 | N104: =N99-N103 | O104: =O99-O103 | P104: =P99-P103 | ... R104: =R99-R103
B105: Net debt / EBITDA | C105: x | F105: ='Model'!F72 | G105: ='Model'!G72 | H105: ='Model'!H72 | I105: =I104/(I66+I88) | J105: =J104/(J66+J88) | K105: =K104/(K66+K88) | L105: =L104/(L66+L88) | M105: =M104/(M66+M88) | N105: =N104/(N66+N88) | O105: =O104/(O66+O88) | P105: =P104/(P66+P88) | ... R105: =R104/(R66+R88)
B106: Diluted shares, end of year | C106: mm | F106: ='Model'!F73 | G106: ='Model'!G73 | H106: ='Model'!H73 | I106: =H106*(1+'Drivers'!$D$33)+I101/I102 | J106: =I106*(1+'Drivers'!$D$33)+J101/J102 | K106: =J106*(1+'Drivers'!$D$33)+K101/K102 | L106: =K106*(1+'Drivers'!$D$33)+L101/L102 | M106: =L106*(1+'Drivers'!$D$33)+M101/M102 | N106: =M106*(1+'Drivers'!$D$33)+N101/N102 | O106: =N106*(1+'Drivers'!$D$33)+O101/O102 | P106: =O106*(1+'Drivers'!$D$33)+P101/P102 | ... R106: =Q106*(1+'Drivers'!$D$33)+R101/R102
B107: net share reduction | C107: % | G107: ='Model'!G74 | H107: ='Model'!H74 | I107: =1-I106/H106 | J107: =1-J106/I106 | K107: =1-K106/J106 | L107: =1-L106/K106 | M107: =1-M106/L106 | N107: =1-N106/M106 | O107: =1-O106/N106 | P107: =1-P106/O106 | ... R107: =1-R106/Q106
B108: Content obligations, year end (memo) | C108: $mm | F108: ='Model'!F75 | G108: ='Model'!G75 | H108: ='Model'!H75
...

Sheet Sources
B1: Netflix, Inc. | Sources, judgments, open items
B2: Full register: outputs/research/nflx_model_assumptions.md
B3: Blue = input Black = formula Green = cross-sheet link $ in millions except per share; shares in millions (post-split)
B6: SOURCES
B7: FY2025 10-K (filed 2026-01-23): https://www.sec.gov/Archives/edgar/data/1065280/000106528026000034/nflx-20251231.htm
B8: Q3 2026 10-Q (filed 2026-10-21): https://www.sec.gov/Archives/edgar/data/1065280/000106528026000291/nflx-20260930.htm
B9: Q3 2026 shareholder letter (8-K Ex. 99.1, 2026-10-20): https://www.sec.gov/Archives/edgar/data/0001065280/000106528026000290/ex991_q326.htm
B10: Q2 2026 letter (2026-07-16), Q1 2026 letter (2026-04-16), Q4 2025 letter (2026-01-20), Q2 2026 10-Q (regional revenue), 8-K Ex. 99.1 on EDGAR.
B11: SEC XBRL company facts, CIK 1065280 (annual and quarterly lines, content obligations, repurchase authorization): https://data.sec.gov/api/xbrl/companyfacts/CIK0001065280.json
B12: Price: Nasdaq close 2026-10-23 $66.29. UST 10Y 4.99% (2026-10-23). Street: Yahoo Finance consensus and price targets 2026-10-23.
B13: Earnings Desk fundamentals for NFLX (SEC facts, closes, Nasdaq consensus; data/earnings_market/fund_NFLX.json) for the 10-year P/E band.
B15: CONTEXT (FACTS)
... B39: 2026-10-23 First build. Not wired into theses.yaml, the Holdings tab or filing_review; a watch model. Projections also feed the Earnings Desk NFLX profile.
